[{"fans": 933, "time": "2023-01-09 18:08:00"}, {"fans": 933, "time": "2023-01-10 06:08:00"}, {"fans": 933, "time": "2023-01-10 18:07:58", "rate1": 0}, {"fans": 932, "time": "2023-01-11 06:07:56", "rate1": -1}, {"fans": 933, "time": "2023-01-11 18:08:24", "rate1": 0}, {"fans": 933, "time": "2023-01-12 06:08:20", "rate1": 1}, {"fans": 932, "time": "2023-01-12 18:08:17", "rate1": -1}, {"fans": 932, "time": "2023-01-13 06:08:15", "rate1": -1}, {"fans": 932, "time": "2023-01-13 18:08:12", "rate1": 0}, {"fans": 931, "time": "2023-01-14 06:08:12", "rate1": -1}, {"fans": 931, "time": "2023-01-14 18:08:15", "rate1": -1}, {"fans": 931, "time": "2023-01-15 06:08:14", "rate1": 0}, {"fans": 931, "time": "2023-01-15 18:08:12", "rate1": 0}, {"fans": 931, "time": "2023-01-16 06:08:13", "rate1": 0}, {"fans": 931, "time": "2023-01-16 18:08:12", "rate1": 0, "rate7": -2}, {"fans": 931, "time": "2023-01-17 06:08:12", "rate1": 0, "rate7": -2}, {"fans": 931, "time": "2023-01-17 18:08:14", "rate1": 0, "rate7": -2}, {"fans": 931, "time": "2023-01-18 06:08:09", "rate1": 0, "rate7": -1}, {"fans": 931, "time": "2023-01-18 18:07:51", "rate1": 0, "rate7": -2}, {"fans": 931, "time": "2023-01-19 06:07:52", "rate1": 0, "rate7": -2}, {"fans": 931, "time": "2023-01-19 18:07:57", "rate1": 0, "rate7": -1}, {"fans": 931, "time": "2023-01-20 06:08:02", "rate1": 0, "rate7": -1}, {"fans": 931, "time": "2023-01-20 18:08:04", "rate1": 0, "rate7": -1}, {"fans": 933, "time": "2023-01-21 06:08:08", "rate1": 2, "rate7": 2}, {"fans": 933, "time": "2023-01-21 18:08:09", "rate1": 2, "rate7": 2}, {"fans": 933, "time": "2023-01-22 06:08:05", "rate1": 0, "rate7": 2}, {"fans": 933, "time": "2023-01-22 18:08:04", "rate1": 0, "rate7": 2}, {"fans": 932, "time": "2023-01-23 06:08:06", "rate1": -1, "rate7": 1}, {"fans": 932, "time": "2023-01-23 18:08:11", "rate1": -1, "rate7": 1}, {"fans": 932, "time": "2023-01-24 06:08:15", "rate1": 0, "rate7": 1}, {"fans": 932, "time": "2023-01-24 18:08:19", "rate1": 0, "rate7": 1}, {"fans": 932, "time": "2023-01-25 06:08:24", "rate1": 0, "rate7": 1}, {"fans": 932, "time": "2023-01-25 18:08:27", "rate1": 0, "rate7": 1}, {"fans": 932, "time": "2023-01-26 06:07:46", "rate1": 0, "rate7": 1}, {"fans": 932, "time": "2023-01-26 18:07:49", "rate1": 0, "rate7": 1}, {"fans": 931, "time": "2023-01-27 06:08:01", "rate1": -1, "rate7": 0}, {"fans": 931, "time": "2023-01-27 18:08:10", "rate1": -1, "rate7": 0}, {"fans": 930, "time": "2023-01-28 06:08:20", "rate1": -1, "rate7": -3}, {"fans": 930, "time": "2023-01-28 18:08:25", "rate1": -1, "rate7": -3}, {"fans": 931, "time": "2023-01-29 06:07:59", "rate1": 1, "rate7": -2}, {"fans": 930, "time": "2023-01-29 18:08:09", "rate1": 0, "rate7": -3}, {"fans": 931, "time": "2023-01-30 06:08:19", "rate1": 0, "rate7": -1}, {"fans": 931, "time": "2023-01-30 18:07:47", "rate1": 1, "rate7": -1}, {"fans": 933, "time": "2023-01-31 06:07:59", "rate1": 2, "rate7": 1}, {"fans": 933, "time": "2023-01-31 18:08:06", "rate1": 2, "rate7": 1}, {"fans": 933, "time": "2023-02-01 06:08:18", "rate1": 0, "rate7": 1}, {"fans": 933, "time": "2023-02-01 18:07:48", "rate1": 0, "rate7": 1}, {"fans": 933, "time": "2023-02-02 06:08:00", "rate1": 0, "rate7": 1}, {"fans": 933, "time": "2023-02-02 18:08:19", "rate1": 0, "rate7": 1}, {"fans": 933, "time": "2023-02-03 06:08:16", "rate1": 0, "rate7": 2}, {"fans": 933, "time": "2023-02-03 18:08:18", "rate1": 0, "rate7": 2}, {"fans": 934, "time": "2023-02-04 06:08:17", "rate1": 1, "rate7": 4}, {"fans": 933, "time": "2023-02-04 18:08:14", "rate1": 0, "rate7": 3}, {"fans": 933, "time": "2023-02-05 06:08:12", "rate1": -1, "rate7": 2}, {"fans": 933, "time": "2023-02-05 18:08:13", "rate1": 0, "rate7": 3}, {"fans": 933, "time": "2023-02-06 06:08:16", "rate1": 0, "rate7": 2}, {"fans": 933, "time": "2023-02-06 18:08:16", "rate1": 0, "rate7": 2}, {"fans": 933, "time": "2023-02-07 06:08:15", "rate1": 0, "rate7": 0}, {"fans": 932, "time": "2023-02-07 18:08:14", "rate1": -1, "rate7": -1}, {"fans": 932, "time": "2023-02-08 06:08:10", "rate1": -1, "rate7": -1}, {"fans": 932, "time": "2023-02-08 18:08:14", "rate1": 0, "rate7": -1}, {"fans": 932, "time": "2023-02-09 06:08:15", "rate1": 0, "rate7": -1}, {"fans": 932, "time": "2023-02-09 18:08:15", "rate1": 0, "rate7": -1}, {"fans": 932, "time": "2023-02-10 06:08:18", "rate1": 0, "rate7": -1}, {"fans": 932, "time": "2023-02-10 18:08:15", "rate1": 0, "rate7": -1}, {"fans": 932, "time": "2023-02-11 06:08:14", "rate1": 0, "rate7": -2}, {"fans": 932, "time": "2023-02-11 18:08:11", "rate1": 0, "rate7": -1}, {"fans": 932, "time": "2023-02-12 06:08:14", "rate1": 0, "rate7": -1}, {"fans": 932, "time": "2023-02-12 18:08:30", "rate1": 0, "rate7": -1}, {"fans": 932, "time": "2023-02-13 06:08:18", "rate1": 0, "rate7": -1}, {"fans": 932, "time": "2023-02-13 18:08:37", "rate1": 0, "rate7": -1}, {"fans": 932, "time": "2023-02-14 06:08:21", "rate1": 0, "rate7": -1}, {"fans": 931, "time": "2023-02-14 18:08:45", "rate1": -1, "rate7": -1}, {"fans": 931, "time": "2023-02-15 06:08:27", "rate1": -1, "rate7": -1}, {"fans": 931, "time": "2023-02-15 18:08:47", "rate1": 0, "rate7": -1}, {"fans": 931, "time": "2023-02-16 06:08:28", "rate1": 0, "rate7": -1}, {"fans": 931, "time": "2023-02-16 18:08:45", "rate1": 0, "rate7": -1}, {"fans": 931, "time": "2023-02-17 06:08:27", "rate1": 0, "rate7": -1}, {"fans": 931, "time": "2023-02-17 18:08:41", "rate1": 0, "rate7": -1}, {"fans": 931, "time": "2023-02-18 06:08:25", "rate1": 0, "rate7": -1}, {"fans": 931, "time": "2023-02-18 18:08:07", "rate1": 0, "rate7": -1}, {"fans": 931, "time": "2023-02-19 06:08:34", "rate1": 0, "rate7": -1}, {"fans": 931, "time": "2023-02-19 18:08:14", "rate1": 0, "rate7": -1}, {"fans": 931, "time": "2023-02-20 06:08:39", "rate1": 0, "rate7": -1}, {"fans": 931, "time": "2023-02-20 18:08:21", "rate1": 0, "rate7": -1}, {"fans": 931, "time": "2023-02-21 06:08:41", "rate1": 0, "rate7": -1}, {"fans": 931, "time": "2023-02-21 18:08:18", "rate1": 0, "rate7": 0}, {"fans": 931, "time": "2023-02-22 06:08:31", "rate1": 0, "rate7": 0}, {"fans": 931, "time": "2023-02-22 18:08:02", "rate1": 0, "rate7": 0}, {"fans": 931, "time": "2023-02-23 06:08:18", "rate1": 0, "rate7": 0}, {"fans": 931, "time": "2023-02-23 18:08:37", "rate1": 0, "rate7": 0}, {"fans": 931, "time": "2023-02-24 06:08:19", "rate1": 0, "rate7": 0}, {"fans": 931, "time": "2023-02-24 18:08:37", "rate1": 0, "rate7": 0}, {"fans": 931, "time": "2023-02-25 06:08:13", "rate1": 0, "rate7": 0}, {"fans": 931, "time": "2023-02-25 18:08:29", "rate1": 0, "rate7": 0}, {"fans": 931, "time": "2023-02-26 06:08:09", "rate1": 0, "rate7": 0}, {"fans": 931, "time": "2023-02-26 18:08:24", "rate1": 0, "rate7": 0}, {"fans": 932, "time": "2023-02-27 06:08:32", "rate1": 1, "rate7": 1}, {"fans": 932, "time": "2023-02-27 18:08:25", "rate1": 1, "rate7": 1}, {"fans": 931, "time": "2023-02-28 06:08:14", "rate1": -1, "rate7": 0}, {"fans": 931, "time": "2023-02-28 18:08:07", "rate1": -1, "rate7": 0}, {"fans": 931, "time": "2023-03-01 06:08:36", "rate1": 0, "rate7": 0}, {"fans": 931, "time": "2023-03-01 18:08:23", "rate1": 0, "rate7": 0}, {"fans": 931, "time": "2023-03-02 06:08:11", "rate1": 0, "rate7": 0}, {"fans": 930, "time": "2023-03-02 18:08:02", "rate1": -1, "rate7": -1}, {"fans": 930, "time": "2023-03-03 06:08:33", "rate1": -1, "rate7": -1}, {"fans": 931, "time": "2023-03-03 18:08:23", "rate1": 1, "rate7": 0}, {"fans": 931, "time": "2023-03-04 06:08:13", "rate1": 1, "rate7": 0}, {"fans": 931, "time": "2023-03-04 18:08:03", "rate1": 0, "rate7": 0}, {"fans": 931, "time": "2023-03-05 06:08:38", "rate1": 0, "rate7": 0}, {"fans": 931, "time": "2023-03-05 18:08:37", "rate1": 0, "rate7": 0}, {"fans": 931, "time": "2023-03-06 06:08:01", "rate1": 0, "rate7": -1}, {"fans": 931, "time": "2023-03-06 18:08:10", "rate1": 0, "rate7": -1}, {"fans": 931, "time": "2023-03-07 06:08:22", "rate1": 0, "rate7": 0}, {"fans": 931, "time": "2023-03-07 18:08:42", "rate1": 0, "rate7": 0}, {"fans": 931, "time": "2023-03-08 06:08:29", "rate1": 0, "rate7": 0}, {"fans": 931, "time": "2023-03-08 18:08:10", "rate1": 0, "rate7": 0}, {"fans": 931, "time": "2023-03-09 06:08:41", "rate1": 0, "rate7": 0}, {"fans": 931, "time": "2023-03-09 18:08:38", "rate1": 0, "rate7": 1}, {"fans": 931, "time": "2023-03-10 06:08:24", "rate1": 0, "rate7": 1}, {"fans": 931, "time": "2023-03-10 18:08:17", "rate1": 0, "rate7": 0}, {"fans": 931, "time": "2023-03-11 06:09:00", "rate1": 0, "rate7": 0}, {"fans": 931, "time": "2023-03-11 18:08:23", "rate1": 0, "rate7": 0}, {"fans": 931, "time": "2023-03-12 06:08:40", "rate1": 0, "rate7": 0}, {"fans": 931, "time": "2023-03-12 18:08:54", "rate1": 0, "rate7": 0}, {"fans": 931, "time": "2023-03-13 06:08:35", "rate1": 0, "rate7": 0}, {"fans": 931, "time": "2023-03-13 18:08:55", "rate1": 0, "rate7": 0}, {"fans": 931, "time": "2023-03-14 06:08:49", "rate1": 0, "rate7": 0}, {"fans": 931, "time": "2023-03-14 18:08:48", "rate1": 0, "rate7": 0}, {"fans": 931, "time": "2023-03-15 06:08:49", "rate1": 0, "rate7": 0}, {"fans": 931, "time": "2023-03-15 18:08:46", "rate1": 0, "rate7": 0}, {"fans": 931, "time": "2023-03-16 06:08:56", "rate1": 0, "rate7": 0}, {"fans": 931, "time": "2023-03-16 18:08:50", "rate1": 0, "rate7": 0}, {"fans": 931, "time": "2023-03-17 06:08:50", "rate1": 0, "rate7": 0}, {"fans": 931, "time": "2023-03-17 18:08:53", "rate1": 0, "rate7": 0}, {"fans": 931, "time": "2023-03-18 06:08:58", "rate1": 0, "rate7": 0}, {"fans": 931, "time": "2023-03-18 18:09:06", "rate1": 0, "rate7": 0}, {"fans": 931, "time": "2023-03-19 06:09:12", "rate1": 0, "rate7": 0}, {"fans": 931, "time": "2023-03-19 18:08:41", "rate1": 0, "rate7": 0}, {"fans": 931, "time": "2023-03-20 06:08:48", "rate1": 0, "rate7": 0}, {"fans": 931, "time": "2023-03-20 18:09:03", "rate1": 0, "rate7": 0}, {"fans": 931, "time": "2023-03-21 06:08:49", "rate1": 0, "rate7": 0}, {"fans": 931, "time": "2023-03-21 18:09:20", "rate1": 0, "rate7": 0}, {"fans": 931, "time": "2023-03-22 06:09:14", "rate1": 0, "rate7": 0}, {"fans": 931, "time": "2023-03-22 18:09:03", "rate1": 0, "rate7": 0}, {"fans": 931, "time": "2023-03-23 06:09:00", "rate1": 0, "rate7": 0}, {"fans": 931, "time": "2023-03-23 18:09:03", "rate1": 0, "rate7": 0}, {"fans": 931, "time": "2023-03-24 06:09:05", "rate1": 0, "rate7": 0}, {"fans": 932, "time": "2023-03-24 18:09:08", "rate1": 1, "rate7": 1}, {"fans": 932, "time": "2023-03-25 06:09:10", "rate1": 1, "rate7": 1}, {"fans": 932, "time": "2023-03-25 18:09:10", "rate1": 0, "rate7": 1}, {"fans": 932, "time": "2023-03-26 06:09:22", "rate1": 0, "rate7": 1}, {"fans": 932, "time": "2023-03-26 18:08:51", "rate1": 0, "rate7": 1}, {"fans": 932, "time": "2023-03-27 06:09:04", "rate1": 0, "rate7": 1}, {"fans": 932, "time": "2023-03-27 18:09:11", "rate1": 0, "rate7": 1}, {"fans": 932, "time": "2023-03-28 06:09:23", "rate1": 0, "rate7": 1}, {"fans": 932, "time": "2023-03-28 18:08:55", "rate1": 0, "rate7": 1}, {"fans": 932, "time": "2023-03-29 06:09:11", "rate1": 0, "rate7": 1}, {"fans": 932, "time": "2023-03-29 18:08:58", "rate1": 0, "rate7": 1}, {"fans": 932, "time": "2023-03-30 06:09:19", "rate1": 0, "rate7": 1}, {"fans": 932, "time": "2023-03-30 18:09:05", "rate1": 0, "rate7": 1}, {"fans": 932, "time": "2023-03-31 06:08:54", "rate1": 0, "rate7": 1}, {"fans": 932, "time": "2023-03-31 18:09:25", "rate1": 0, "rate7": 0}, {"fans": 932, "time": "2023-04-01 06:09:16", "rate1": 0, "rate7": 0}, {"fans": 932, "time": "2023-04-01 18:09:14", "rate1": 0, "rate7": 0}, {"fans": 932, "time": "2023-04-02 06:09:19", "rate1": 0, "rate7": 0}, {"fans": 932, "time": "2023-04-02 18:09:26", "rate1": 0, "rate7": 0}, {"fans": 932, "time": "2023-04-03 06:08:49", "rate1": 0, "rate7": 0}, {"fans": 932, "time": "2023-04-03 18:08:53", "rate1": 0, "rate7": 0}, {"fans": 932, "time": "2023-04-04 06:08:56", "rate1": 0, "rate7": 0}, {"fans": 932, "time": "2023-04-04 18:09:11", "rate1": 0, "rate7": 0}, {"fans": 932, "time": "2023-04-05 06:09:27", "rate1": 0, "rate7": 0}, {"fans": 932, "time": "2023-04-05 18:09:05", "rate1": 0, "rate7": 0}, {"fans": 932, "time": "2023-04-06 06:09:01", "rate1": 0, "rate7": 0}, {"fans": 932, "time": "2023-04-06 18:09:38", "rate1": 0, "rate7": 0}, {"fans": 932, "time": "2023-04-07 06:09:32", "rate1": 0, "rate7": 0}, {"fans": 932, "time": "2023-04-07 18:09:24", "rate1": 0, "rate7": 0}, {"fans": 932, "time": "2023-04-08 06:09:16", "rate1": 0, "rate7": 0}, {"fans": 932, "time": "2023-04-08 18:09:10", "rate1": 0, "rate7": 0}, {"fans": 932, "time": "2023-04-09 06:09:03", "rate1": 0, "rate7": 0}, {"fans": 932, "time": "2023-04-09 18:09:43", "rate1": 0, "rate7": 0}, {"fans": 932, "time": "2023-04-10 06:09:09", "rate1": 0, "rate7": 0}, {"fans": 932, "time": "2023-04-10 18:09:09", "rate1": 0, "rate7": 0}, {"fans": 932, "time": "2023-04-11 06:09:16", "rate1": 0, "rate7": 0}, {"fans": 932, "time": "2023-04-11 18:09:15", "rate1": 0, "rate7": 0}, {"fans": 932, "time": "2023-04-12 06:09:17", "rate1": 0, "rate7": 0}, {"fans": 931, "time": "2023-04-12 18:09:23", "rate1": -1, "rate7": -1}, {"fans": 931, "time": "2023-04-13 06:09:33", "rate1": -1, "rate7": -1}, {"fans": 931, "time": "2023-04-13 18:09:46", "rate1": 0, "rate7": -1}, {"fans": 931, "time": "2023-04-14 06:09:20", "rate1": 0, "rate7": -1}, {"fans": 931, "time": "2023-04-14 18:09:34", "rate1": 0, "rate7": -1}, {"fans": 931, "time": "2023-04-15 06:09:29", "rate1": 0, "rate7": -1}, {"fans": 931, "time": "2023-04-15 18:09:46", "rate1": 0, "rate7": -1}, {"fans": 931, "time": "2023-04-16 06:10:10", "rate1": 0, "rate7": -1}, {"fans": 931, "time": "2023-04-16 18:10:06", "rate1": 0, "rate7": -1}, {"fans": 931, "time": "2023-04-17 06:09:59", "rate1": 0, "rate7": -1}, {"fans": 931, "time": "2023-04-17 18:10:03", "rate1": 0, "rate7": -1}, {"fans": 931, "time": "2023-04-18 06:09:47", "rate1": 0, "rate7": -1}, {"fans": 931, "time": "2023-04-18 18:09:42", "rate1": 0, "rate7": -1}, {"fans": 931, "time": "2023-04-19 06:09:41", "rate1": 0, "rate7": -1}, {"fans": 931, "time": "2023-04-19 18:10:09", "rate1": 0, "rate7": 0}, {"fans": 931, "time": "2023-04-20 06:10:03", "rate1": 0, "rate7": 0}, {"fans": 931, "time": "2023-04-20 18:10:01", "rate1": 0, "rate7": 0}, {"fans": 931, "time": "2023-04-21 06:10:08", "rate1": 0, "rate7": 0}, {"fans": 931, "time": "2023-04-21 18:10:40", "rate1": 0, "rate7": 0}, {"fans": 932, "time": "2023-04-22 06:10:42", "rate1": 1, "rate7": 1}, {"fans": 932, "time": "2023-04-22 18:10:36", "rate1": 1, "rate7": 1}, {"fans": 932, "time": "2023-04-23 06:10:29", "rate1": 0, "rate7": 1}, {"fans": 932, "time": "2023-04-23 18:10:25", "rate1": 0, "rate7": 1}, {"fans": 932, "time": "2023-04-24 06:10:21", "rate1": 0, "rate7": 1}, {"fans": 932, "time": "2023-04-24 18:11:02", "rate1": 0, "rate7": 1}, {"fans": 933, "time": "2023-04-25 06:10:23", "rate1": 1, "rate7": 2}, {"fans": 933, "time": "2023-04-25 18:11:03", "rate1": 1, "rate7": 2}, {"fans": 933, "time": "2023-04-26 06:10:40", "rate1": 0, "rate7": 2}, {"fans": 933, "time": "2023-04-26 18:10:57", "rate1": 0, "rate7": 2}, {"fans": 933, "time": "2023-04-27 06:10:36", "rate1": 0, "rate7": 2}, {"fans": 933, "time": "2023-04-27 18:10:52", "rate1": 0, "rate7": 2}, {"fans": 933, "time": "2023-04-28 06:10:33", "rate1": 0, "rate7": 2}, {"fans": 933, "time": "2023-04-28 18:10:53", "rate1": 0, "rate7": 2}, {"fans": 933, "time": "2023-04-29 06:10:32", "rate1": 0, "rate7": 1}, {"fans": 933, "time": "2023-04-29 18:10:47", "rate1": 0, "rate7": 1}, {"fans": 933, "time": "2023-04-30 06:10:27", "rate1": 0, "rate7": 1}, {"fans": 933, "time": "2023-04-30 18:10:43", "rate1": 0, "rate7": 1}, {"fans": 933, "time": "2023-05-01 06:11:02", "rate1": 0, "rate7": 1}, {"fans": 933, "time": "2023-05-01 18:11:01", "rate1": 0, "rate7": 1}, {"fans": 932, "time": "2023-05-02 06:11:02", "rate1": -1, "rate7": -1}, {"fans": 939, "time": "2023-05-02 18:11:07", "rate1": 6, "rate7": 6}, {"fans": 941, "time": "2023-05-03 06:10:32", "rate1": 9, "rate7": 8}, {"fans": 942, "time": "2023-05-03 18:10:40", "rate1": 3, "rate7": 9}, {"fans": 942, "time": "2023-05-04 06:10:52", "rate1": 1, "rate7": 9}, {"fans": 942, "time": "2023-05-04 18:11:03", "rate1": 0, "rate7": 9}, {"fans": 946, "time": "2023-05-05 06:10:32", "rate1": 4, "rate7": 13}, {"fans": 946, "time": "2023-05-05 18:10:41", "rate1": 4, "rate7": 13}, {"fans": 949, "time": "2023-05-06 06:10:53", "rate1": 3, "rate7": 16}, {"fans": 953, "time": "2023-05-06 18:11:07", "rate1": 7, "rate7": 20}, {"fans": 954, "time": "2023-05-07 06:10:54", "rate1": 5, "rate7": 21}, {"fans": 954, "time": "2023-05-07 18:11:29", "rate1": 1, "rate7": 21}, {"fans": 956, "time": "2023-05-08 06:10:53", "rate1": 2, "rate7": 23}, {"fans": 956, "time": "2023-05-08 18:11:09", "rate1": 2, "rate7": 23}, {"fans": 957, "time": "2023-05-09 06:11:24", "rate1": 1, "rate7": 25}, {"fans": 957, "time": "2023-05-09 18:11:08", "rate1": 1, "rate7": 18}, {"fans": 957, "time": "2023-05-10 06:11:30", "rate1": 0, "rate7": 16}, {"fans": 957, "time": "2023-05-10 18:11:32", "rate1": 0, "rate7": 15}, {"fans": 961, "time": "2023-05-11 06:11:12", "rate1": 4, "rate7": 19}, {"fans": 961, "time": "2023-05-11 18:11:00", "rate1": 4, "rate7": 19}, {"fans": 961, "time": "2023-05-12 06:11:45", "rate1": 0, "rate7": 15}, {"fans": 961, "time": "2023-05-12 18:11:12", "rate1": 0, "rate7": 15}, {"fans": 961, "time": "2023-05-13 06:11:28", "rate1": 0, "rate7": 12}, {"fans": 962, "time": "2023-05-13 18:11:47", "rate1": 1, "rate7": 9}, {"fans": 962, "time": "2023-05-14 06:11:24", "rate1": 1, "rate7": 8}, {"fans": 962, "time": "2023-05-14 18:11:39", "rate1": 0, "rate7": 8}, {"fans": 962, "time": "2023-05-15 06:11:18", "rate1": 0, "rate7": 6}, {"fans": 962, "time": "2023-05-15 18:11:39", "rate1": 0, "rate7": 6}, {"fans": 962, "time": "2023-05-16 06:11:24", "rate1": 0, "rate7": 5}, {"fans": 962, "time": "2023-05-16 18:11:46", "rate1": 0, "rate7": 5}, {"fans": 962, "time": "2023-05-17 06:11:38", "rate1": 0, "rate7": 5}, {"fans": 963, "time": "2023-05-17 18:11:31", "rate1": 1, "rate7": 6}, {"fans": 963, "time": "2023-05-18 06:11:25", "rate1": 1, "rate7": 2}, {"fans": 963, "time": "2023-05-18 18:12:00", "rate1": 0, "rate7": 2}, {"fans": 964, "time": "2023-05-19 06:11:55", "rate1": 1, "rate7": 3}, {"fans": 964, "time": "2023-05-19 18:11:41", "rate1": 1, "rate7": 3}, {"fans": 965, "time": "2023-05-20 06:11:47", "rate1": 1, "rate7": 4}, {"fans": 965, "time": "2023-05-20 18:11:54", "rate1": 1, "rate7": 3}, {"fans": 964, "time": "2023-05-21 06:11:28", "rate1": -1, "rate7": 2}, {"fans": 964, "time": "2023-05-21 18:11:47", "rate1": -1, "rate7": 2}, {"fans": 964, "time": "2023-05-22 06:12:03", "rate1": 0, "rate7": 2}, {"fans": 964, "time": "2023-05-22 18:11:39", "rate1": 0, "rate7": 2}, {"fans": 965, "time": "2023-05-23 06:12:00", "rate1": 1, "rate7": 3}, {"fans": 965, "time": "2023-05-23 18:11:38", "rate1": 1, "rate7": 3}, {"fans": 965, "time": "2023-05-24 06:12:06", "rate1": 0, "rate7": 3}, {"fans": 965, "time": "2023-05-24 18:11:55", "rate1": 0, "rate7": 2}, {"fans": 965, "time": "2023-05-25 06:11:47", "rate1": 0, "rate7": 2}, {"fans": 964, "time": "2023-05-25 18:11:37", "rate1": -1, "rate7": 1}, {"fans": 964, "time": "2023-05-26 06:12:09", "rate1": -1, "rate7": 0}, {"fans": 964, "time": "2023-05-26 18:12:00", "rate1": 0, "rate7": 0}, {"fans": 964, "time": "2023-05-27 06:11:49", "rate1": 0, "rate7": -1}, {"fans": 965, "time": "2023-05-27 18:11:42", "rate1": 1, "rate7": 0}, {"fans": 964, "time": "2023-05-28 06:11:38", "rate1": 0, "rate7": 0}, {"fans": 964, "time": "2023-05-28 18:11:39", "rate1": -1, "rate7": 0}, {"fans": 964, "time": "2023-05-29 06:11:42", "rate1": 0, "rate7": 0}, {"fans": 964, "time": "2023-05-29 18:11:41", "rate1": 0, "rate7": 0}, {"fans": 964, "time": "2023-05-30 06:11:44", "rate1": 0, "rate7": -1}, {"fans": 965, "time": "2023-05-30 18:11:44", "rate1": 1, "rate7": 0}, {"fans": 965, "time": "2023-05-31 06:11:46", "rate1": 1, "rate7": 0}, {"fans": 965, "time": "2023-05-31 18:11:50", "rate1": 0, "rate7": 0}, {"fans": 965, "time": "2023-06-01 06:11:50", "rate1": 0, "rate7": 0}, {"fans": 965, "time": "2023-06-01 18:11:50", "rate1": 0, "rate7": 1}, {"fans": 965, "time": "2023-06-02 06:11:55", "rate1": 0, "rate7": 1}, {"fans": 965, "time": "2023-06-02 18:12:00", "rate1": 0, "rate7": 1}, {"fans": 965, "time": "2023-06-03 06:11:34", "rate1": 0, "rate7": 1}, {"fans": 965, "time": "2023-06-03 18:11:52", "rate1": 0, "rate7": 0}, {"fans": 965, "time": "2023-06-04 06:12:09", "rate1": 0, "rate7": 1}, {"fans": 965, "time": "2023-06-04 18:11:58", "rate1": 0, "rate7": 1}, {"fans": 964, "time": "2023-06-05 06:11:40", "rate1": -1, "rate7": 0}, {"fans": 964, "time": "2023-06-05 18:12:08", "rate1": -1, "rate7": 0}, {"fans": 964, "time": "2023-06-06 06:12:03", "rate1": 0, "rate7": 0}, {"fans": 964, "time": "2023-06-06 18:12:06", "rate1": 0, "rate7": -1}, {"fans": 964, "time": "2023-06-07 06:12:15", "rate1": 0, "rate7": -1}, {"fans": 964, "time": "2023-06-07 18:11:56", "rate1": 0, "rate7": -1}, {"fans": 964, "time": "2023-06-08 06:12:24", "rate1": 0, "rate7": -1}, {"fans": 965, "time": "2023-06-08 18:12:19", "rate1": 1, "rate7": 0}, {"fans": 966, "time": "2023-06-09 06:12:11", "rate1": 2, "rate7": 1}, {"fans": 965, "time": "2023-06-09 18:12:04", "rate1": 0, "rate7": 0}, {"fans": 964, "time": "2023-06-10 06:11:58", "rate1": -2, "rate7": -1}, {"fans": 963, "time": "2023-06-10 18:12:30", "rate1": -2, "rate7": -2}, {"fans": 963, "time": "2023-06-11 06:12:25", "rate1": -1, "rate7": -2}, {"fans": 963, "time": "2023-06-11 18:12:31", "rate1": 0, "rate7": -2}, {"fans": 963, "time": "2023-06-12 06:12:00", "rate1": 0, "rate7": -1}, {"fans": 963, "time": "2023-06-12 18:12:09", "rate1": 0, "rate7": -1}, {"fans": 963, "time": "2023-06-13 06:12:18", "rate1": 0, "rate7": -1}, {"fans": 963, "time": "2023-06-13 18:12:25", "rate1": 0, "rate7": -1}, {"fans": 963, "time": "2023-06-14 06:11:51", "rate1": 0, "rate7": -1}, {"fans": 963, "time": "2023-06-14 18:12:05", "rate1": 0, "rate7": -1}, {"fans": 963, "time": "2023-06-15 06:12:25", "rate1": 0, "rate7": -1}, {"fans": 963, "time": "2023-06-15 18:12:11", "rate1": 0, "rate7": -2}, {"fans": 963, "time": "2023-06-16 06:12:05", "rate1": 0, "rate7": -3}, {"fans": 963, "time": "2023-06-16 18:11:56", "rate1": 0, "rate7": -2}, {"fans": 963, "time": "2023-06-17 06:12:30", "rate1": 0, "rate7": -1}, {"fans": 963, "time": "2023-06-17 18:12:20", "rate1": 0, "rate7": 0}, {"fans": 963, "time": "2023-06-18 06:12:17", "rate1": 0, "rate7": 0}, {"fans": 963, "time": "2023-06-18 18:12:20", "rate1": 0, "rate7": 0}, {"fans": 963, "time": "2023-06-19 06:12:17", "rate1": 0, "rate7": 0}, {"fans": 963, "time": "2023-06-19 18:12:24", "rate1": 0, "rate7": 0}, {"fans": 963, "time": "2023-06-20 06:12:26", "rate1": 0, "rate7": 0}, {"fans": 963, "time": "2023-06-20 18:12:30", "rate1": 0, "rate7": 0}, {"fans": 963, "time": "2023-06-21 06:12:46", "rate1": 0, "rate7": 0}, {"fans": 963, "time": "2023-06-21 18:12:15", "rate1": 0, "rate7": 0}, {"fans": 963, "time": "2023-06-22 06:12:29", "rate1": 0, "rate7": 0}, {"fans": 963, "time": "2023-06-22 18:12:39", "rate1": 0, "rate7": 0}, {"fans": 963, "time": "2023-06-23 06:12:16", "rate1": 0, "rate7": 0}, {"fans": 963, "time": "2023-06-23 18:12:44", "rate1": 0, "rate7": 0}, {"fans": 963, "time": "2023-06-24 06:12:32", "rate1": 0, "rate7": 0}, {"fans": 963, "time": "2023-06-24 18:12:28", "rate1": 0, "rate7": 0}, {"fans": 963, "time": "2023-06-25 06:12:27", "rate1": 0, "rate7": 0}, {"fans": 963, "time": "2023-06-25 18:12:28", "rate1": 0, "rate7": 0}, {"fans": 963, "time": "2023-06-26 06:12:36", "rate1": 0, "rate7": 0}, {"fans": 963, "time": "2023-06-26 18:12:45", "rate1": 0, "rate7": 0}, {"fans": 963, "time": "2023-06-27 06:13:01", "rate1": 0, "rate7": 0}, {"fans": 963, "time": "2023-06-27 18:12:44", "rate1": 0, "rate7": 0}, {"fans": 963, "time": "2023-06-28 06:12:29", "rate1": 0, "rate7": 0}, {"fans": 963, "time": "2023-06-28 18:12:51", "rate1": 0, "rate7": 0}, {"fans": 963, "time": "2023-06-29 06:12:32", "rate1": 0, "rate7": 0}, {"fans": 963, "time": "2023-06-29 18:12:50", "rate1": 0, "rate7": 0}, {"fans": 963, "time": "2023-06-30 06:12:28", "rate1": 0, "rate7": 0}, {"fans": 963, "time": "2023-06-30 18:12:44", "rate1": 0, "rate7": 0}, {"fans": 963, "time": "2023-07-01 06:13:07", "rate1": 0, "rate7": 0}, {"fans": 963, "time": "2023-07-01 18:12:50", "rate1": 0, "rate7": 0}, {"fans": 963, "time": "2023-07-02 06:12:35", "rate1": 0, "rate7": 0}, {"fans": 963, "time": "2023-07-02 18:12:40", "rate1": 0, "rate7": 0}, {"fans": 962, "time": "2023-07-03 06:12:53", "rate1": -1, "rate7": -1}, {"fans": 962, "time": "2023-07-03 18:13:04", "rate1": -1, "rate7": -1}, {"fans": 961, "time": "2023-07-04 06:12:36", "rate1": -1, "rate7": -2}, {"fans": 961, "time": "2023-07-04 18:12:50", "rate1": -1, "rate7": -2}, {"fans": 961, "time": "2023-07-05 06:13:02", "rate1": 0, "rate7": -2}, {"fans": 961, "time": "2023-07-05 18:12:42", "rate1": 0, "rate7": -2}, {"fans": 960, "time": "2023-07-06 06:13:08", "rate1": -1, "rate7": -3}, {"fans": 960, "time": "2023-07-06 18:12:44", "rate1": -1, "rate7": -3}, {"fans": 960, "time": "2023-07-07 06:13:06", "rate1": 0, "rate7": -3}, {"fans": 960, "time": "2023-07-07 18:13:01", "rate1": 0, "rate7": -3}, {"fans": 960, "time": "2023-07-08 06:12:41", "rate1": 0, "rate7": -3}, {"fans": 960, "time": "2023-07-08 18:13:07", "rate1": 0, "rate7": -3}, {"fans": 960, "time": "2023-07-09 06:12:55", "rate1": 0, "rate7": -3}, {"fans": 960, "time": "2023-07-09 18:12:43", "rate1": 0, "rate7": -3}, {"fans": 960, "time": "2023-07-10 06:13:11", "rate1": 0, "rate7": -2}, {"fans": 961, "time": "2023-07-10 18:12:58", "rate1": 1, "rate7": -1}, {"fans": 961, "time": "2023-07-11 06:12:46", "rate1": 1, "rate7": 0}, {"fans": 961, "time": "2023-07-11 18:12:33", "rate1": 0, "rate7": 0}, {"fans": 963, "time": "2023-07-12 06:13:02", "rate1": 2, "rate7": 2}, {"fans": 964, "time": "2023-07-12 18:12:49", "rate1": 3, "rate7": 3}, {"fans": 964, "time": "2023-07-13 06:12:37", "rate1": 1, "rate7": 4}, {"fans": 965, "time": "2023-07-13 18:13:08", "rate1": 1, "rate7": 5}, {"fans": 965, "time": "2023-07-14 06:13:05", "rate1": 1, "rate7": 5}, {"fans": 965, "time": "2023-07-14 18:13:06", "rate1": 0, "rate7": 5}, {"fans": 965, "time": "2023-07-15 06:13:05", "rate1": 0, "rate7": 5}, {"fans": 965, "time": "2023-07-15 18:13:04", "rate1": 0, "rate7": 5}, {"fans": 965, "time": "2023-07-16 06:13:05", "rate1": 0, "rate7": 5}, {"fans": 965, "time": "2023-07-16 18:12:33", "rate1": 0, "rate7": 5}, {"fans": 964, "time": "2023-07-17 06:12:38", "rate1": -1, "rate7": 4}, {"fans": 965, "time": "2023-07-17 18:12:44", "rate1": 0, "rate7": 4}, {"fans": 965, "time": "2023-07-18 06:12:49", "rate1": 1, "rate7": 4}, {"fans": 965, "time": "2023-07-18 18:12:55", "rate1": 0, "rate7": 4}, {"fans": 965, "time": "2023-07-19 06:13:03", "rate1": 0, "rate7": 2}, {"fans": 967, "time": "2023-07-19 18:13:03", "rate1": 2, "rate7": 3}, {"fans": 967, "time": "2023-07-20 06:13:08", "rate1": 2, "rate7": 3}, {"fans": 967, "time": "2023-07-20 18:12:31", "rate1": 0, "rate7": 2}, {"fans": 968, "time": "2023-07-21 06:12:37", "rate1": 1, "rate7": 3}, {"fans": 968, "time": "2023-07-21 18:12:45", "rate1": 1, "rate7": 3}, {"fans": 969, "time": "2023-07-22 06:12:56", "rate1": 1, "rate7": 4}, {"fans": 969, "time": "2023-07-22 18:13:06", "rate1": 1, "rate7": 4}, {"fans": 970, "time": "2023-07-23 06:12:35", "rate1": 1, "rate7": 5}, {"fans": 970, "time": "2023-07-23 18:12:45", "rate1": 1, "rate7": 5}, {"fans": 970, "time": "2023-07-24 06:12:57", "rate1": 0, "rate7": 6}, {"fans": 971, "time": "2023-07-24 18:13:08", "rate1": 1, "rate7": 6}, {"fans": 971, "time": "2023-07-25 06:12:39", "rate1": 1, "rate7": 6}, {"fans": 971, "time": "2023-07-25 18:13:01", "rate1": 0, "rate7": 6}, {"fans": 971, "time": "2023-07-26 06:12:36", "rate1": 0, "rate7": 6}, {"fans": 971, "time": "2023-07-26 18:12:56", "rate1": 0, "rate7": 4}, {"fans": 974, "time": "2023-07-27 06:12:40", "rate1": 3, "rate7": 7}, {"fans": 975, "time": "2023-07-27 18:12:42", "rate1": 4, "rate7": 8}, {"fans": 975, "time": "2023-07-28 06:12:39", "rate1": 1, "rate7": 7}, {"fans": 975, "time": "2023-07-28 18:12:43", "rate1": 0, "rate7": 7}, {"fans": 976, "time": "2023-07-29 06:12:46", "rate1": 1, "rate7": 7}, {"fans": 976, "time": "2023-07-29 18:12:53", "rate1": 1, "rate7": 7}, {"fans": 976, "time": "2023-07-30 06:13:07", "rate1": 0, "rate7": 6}, {"fans": 976, "time": "2023-07-30 18:12:45", "rate1": 0, "rate7": 6}, {"fans": 976, "time": "2023-07-31 06:13:07", "rate1": 0, "rate7": 6}, {"fans": 976, "time": "2023-07-31 18:12:52", "rate1": 0, "rate7": 5}, {"fans": 976, "time": "2023-08-01 06:12:38", "rate1": 0, "rate7": 5}, {"fans": 976, "time": "2023-08-01 18:13:12", "rate1": 0, "rate7": 5}, {"fans": 976, "time": "2023-08-02 06:13:01", "rate1": 0, "rate7": 5}, {"fans": 977, "time": "2023-08-02 18:13:16", "rate1": 1, "rate7": 6}, {"fans": 977, "time": "2023-08-03 06:13:31", "rate1": 1, "rate7": 3}, {"fans": 977, "time": "2023-08-03 18:13:04", "rate1": 0, "rate7": 2}, {"fans": 977, "time": "2023-08-04 06:13:26", "rate1": 0, "rate7": 2}, {"fans": 979, "time": "2023-08-04 18:13:16", "rate1": 2, "rate7": 4}, {"fans": 980, "time": "2023-08-05 06:13:12", "rate1": 3, "rate7": 4}, {"fans": 980, "time": "2023-08-05 18:13:14", "rate1": 1, "rate7": 4}, {"fans": 980, "time": "2023-08-06 06:13:21", "rate1": 0, "rate7": 4}, {"fans": 980, "time": "2023-08-06 18:13:36", "rate1": 0, "rate7": 4}, {"fans": 979, "time": "2023-08-07 07:25:56", "rate1": -1, "rate7": 3}, {"fans": 979, "time": "2023-08-07 18:13:50", "rate1": -1, "rate7": 3}, {"fans": 979, "time": "2023-08-08 06:13:34", "rate1": 0, "rate7": 3}, {"fans": 979, "time": "2023-08-08 18:13:56", "rate1": 0, "rate7": 3}, {"fans": 979, "time": "2023-08-09 06:13:51", "rate1": 0, "rate7": 3}, {"fans": 979, "time": "2023-08-09 18:13:48", "rate1": 0, "rate7": 2}, {"fans": 979, "time": "2023-08-10 06:13:51", "rate1": 0, "rate7": 2}, {"fans": 979, "time": "2023-08-10 18:14:04", "rate1": 0, "rate7": 2}, {"fans": 978, "time": "2023-08-11 06:13:43", "rate1": -1, "rate7": 1}, {"fans": 978, "time": "2023-08-11 18:14:01", "rate1": -1, "rate7": -1}, {"fans": 978, "time": "2023-08-12 06:13:46", "rate1": 0, "rate7": -2}, {"fans": 978, "time": "2023-08-12 18:13:51", "rate1": 0, "rate7": -2}, {"fans": 978, "time": "2023-08-13 06:13:52", "rate1": 0, "rate7": -2}, {"fans": 978, "time": "2023-08-13 18:14:05", "rate1": 0, "rate7": -2}, {"fans": 978, "time": "2023-08-14 06:14:00", "rate1": 0, "rate7": -1}, {"fans": 978, "time": "2023-08-14 18:14:30", "rate1": 0, "rate7": -1}, {"fans": 978, "time": "2023-08-15 06:14:27", "rate1": 0, "rate7": -1}, {"fans": 978, "time": "2023-08-15 18:14:15", "rate1": 0, "rate7": -1}, {"fans": 978, "time": "2023-08-16 06:14:57", "rate1": 0, "rate7": -1}, {"fans": 978, "time": "2023-08-16 18:14:30", "rate1": 0, "rate7": -1}, {"fans": 978, "time": "2023-08-17 06:14:45", "rate1": 0, "rate7": -1}, {"fans": 978, "time": "2023-08-17 18:14:25", "rate1": 0, "rate7": -1}, {"fans": 977, "time": "2023-08-18 06:14:55", "rate1": -1, "rate7": -1}, {"fans": 977, "time": "2023-08-18 18:14:43", "rate1": -1, "rate7": -1}, {"fans": 978, "time": "2023-08-19 06:14:38", "rate1": 1, "rate7": 0}, {"fans": 978, "time": "2023-08-19 18:14:37", "rate1": 1, "rate7": 0}, {"fans": 977, "time": "2023-08-20 06:14:42", "rate1": -1, "rate7": -1}, {"fans": 977, "time": "2023-08-20 18:14:51", "rate1": -1, "rate7": -1}, {"fans": 977, "time": "2023-08-21 06:15:03", "rate1": 0, "rate7": -1}, {"fans": 977, "time": "2023-08-21 18:14:40", "rate1": 0, "rate7": -1}, {"fans": 976, "time": "2023-08-22 06:15:03", "rate1": -1, "rate7": -2}, {"fans": 976, "time": "2023-08-22 18:14:45", "rate1": -1, "rate7": -2}, {"fans": 976, "time": "2023-08-23 06:15:11", "rate1": 0, "rate7": -2}, {"fans": 975, "time": "2023-08-23 18:15:07", "rate1": -1, "rate7": -3}, {"fans": 975, "time": "2023-08-24 06:15:13", "rate1": -1, "rate7": -3}, {"fans": 974, "time": "2023-08-24 19:34:59", "rate1": -1, "rate7": -4}, {"fans": 974, "time": "2023-08-25 06:15:08", "rate1": -1, "rate7": -3}, {"fans": 974, "time": "2023-08-25 18:14:59", "rate1": 0, "rate7": -3}, {"fans": 974, "time": "2023-08-26 06:15:00", "rate1": 0, "rate7": -4}, {"fans": 974, "time": "2023-08-26 18:15:03", "rate1": 0, "rate7": -4}, {"fans": 974, "time": "2023-08-27 06:15:15", "rate1": 0, "rate7": -3}, {"fans": 974, "time": "2023-08-27 18:15:26", "rate1": 0, "rate7": -3}, {"fans": 974, "time": "2023-08-28 06:15:11", "rate1": 0, "rate7": -3}, {"fans": 974, "time": "2023-08-28 18:15:35", "rate1": 0, "rate7": -3}, {"fans": 974, "time": "2023-08-29 06:15:02", "rate1": 0, "rate7": -2}, {"fans": 974, "time": "2023-08-29 18:15:05", "rate1": 0, "rate7": -2}, {"fans": 974, "time": "2023-08-30 06:15:16", "rate1": 0, "rate7": -2}, {"fans": 974, "time": "2023-08-30 18:15:26", "rate1": 0, "rate7": -1}, {"fans": 974, "time": "2023-08-31 06:14:58", "rate1": 0, "rate7": -1}, {"fans": 974, "time": "2023-08-31 18:15:11", "rate1": 0, "rate7": 0}, {"fans": 974, "time": "2023-09-01 06:15:29", "rate1": 0, "rate7": 0}, {"fans": 974, "time": "2023-09-01 18:15:08", "rate1": 0, "rate7": 0}, {"fans": 974, "time": "2023-09-02 06:15:20", "rate1": 0, "rate7": 0}, {"fans": 974, "time": "2023-09-02 18:14:55", "rate1": 0, "rate7": 0}, {"fans": 974, "time": "2023-09-03 06:15:08", "rate1": 0, "rate7": 0}, {"fans": 974, "time": "2023-09-03 18:15:13", "rate1": 0, "rate7": 0}, {"fans": 974, "time": "2023-09-04 06:15:20", "rate1": 0, "rate7": 0}, {"fans": 974, "time": "2023-09-04 18:15:32", "rate1": 0, "rate7": 0}, {"fans": 974, "time": "2023-09-05 06:15:10", "rate1": 0, "rate7": 0}, {"fans": 974, "time": "2023-09-05 18:15:22", "rate1": 0, "rate7": 0}, {"fans": 974, "time": "2023-09-06 06:15:01", "rate1": 0, "rate7": 0}, {"fans": 973, "time": "2023-09-06 18:15:21", "rate1": -1, "rate7": -1}, {"fans": 973, "time": "2023-09-07 06:15:39", "rate1": -1, "rate7": -1}, {"fans": 973, "time": "2023-09-07 18:15:27", "rate1": 0, "rate7": -1}, {"fans": 973, "time": "2023-09-08 18:15:26", "rate1": 0, "rate7": -1}, {"fans": 973, "time": "2023-09-09 06:15:20", "rate1": 0, "rate7": -1}, {"fans": 972, "time": "2023-09-09 18:15:25", "rate1": -1, "rate7": -2}, {"fans": 972, "time": "2023-09-10 06:15:31", "rate1": -1, "rate7": -2}, {"fans": 972, "time": "2023-09-10 18:15:00", "rate1": 0, "rate7": -2}, {"fans": 972, "time": "2023-09-11 06:15:16", "rate1": 0, "rate7": -2}, {"fans": 972, "time": "2023-09-11 18:15:41", "rate1": 0, "rate7": -2}, {"fans": 972, "time": "2023-09-12 06:15:26", "rate1": 0, "rate7": -2}, {"fans": 972, "time": "2023-09-12 18:15:11", "rate1": 0, "rate7": -2}, {"fans": 972, "time": "2023-09-13 06:15:42", "rate1": 0, "rate7": -2}, {"fans": 972, "time": "2023-09-13 18:15:47", "rate1": 0, "rate7": -2}, {"fans": 972, "time": "2023-09-14 06:15:12", "rate1": 0, "rate7": -1}, {"fans": 972, "time": "2023-09-14 18:15:27", "rate1": 0, "rate7": -1}, {"fans": 972, "time": "2023-09-15 06:15:58", "rate1": 0, "rate7": -1}, {"fans": 972, "time": "2023-09-15 18:16:03", "rate1": 0, "rate7": -1}, {"fans": 972, "time": "2023-09-16 06:15:29", "rate1": 0, "rate7": -1}, {"fans": 972, "time": "2023-09-16 18:15:31", "rate1": 0, "rate7": 0}, {"fans": 972, "time": "2023-09-17 06:15:35", "rate1": 0, "rate7": 0}, {"fans": 972, "time": "2023-09-17 18:15:53", "rate1": 0, "rate7": 0}, {"fans": 972, "time": "2023-09-18 06:15:32", "rate1": 0, "rate7": 0}, {"fans": 972, "time": "2023-09-18 18:15:55", "rate1": 0, "rate7": 0}, {"fans": 972, "time": "2023-09-19 06:15:39", "rate1": 0, "rate7": 0}, {"fans": 972, "time": "2023-09-19 18:16:03", "rate1": 0, "rate7": 0}, {"fans": 972, "time": "2023-09-20 06:15:48", "rate1": 0, "rate7": 0}, {"fans": 972, "time": "2023-09-20 18:15:32", "rate1": 0, "rate7": 0}, {"fans": 972, "time": "2023-09-21 06:15:58", "rate1": 0, "rate7": 0}, {"fans": 972, "time": "2023-09-21 18:15:47", "rate1": 0, "rate7": 0}, {"fans": 972, "time": "2023-09-22 06:15:37", "rate1": 0, "rate7": 0}, {"fans": 972, "time": "2023-09-22 18:15:26", "rate1": 0, "rate7": 0}, {"fans": 972, "time": "2023-09-23 06:15:55", "rate1": 0, "rate7": 0}, {"fans": 971, "time": "2023-09-23 18:15:45", "rate1": -1, "rate7": -1}, {"fans": 971, "time": "2023-09-24 06:15:35", "rate1": -1, "rate7": -1}, {"fans": 971, "time": "2023-09-24 18:15:25", "rate1": 0, "rate7": -1}, {"fans": 971, "time": "2023-09-25 06:15:56", "rate1": 0, "rate7": -1}, {"fans": 971, "time": "2023-09-25 18:15:50", "rate1": 0, "rate7": -1}, {"fans": 971, "time": "2023-09-26 06:15:46", "rate1": 0, "rate7": -1}, {"fans": 971, "time": "2023-09-26 18:15:58", "rate1": 0, "rate7": -1}, {"fans": 971, "time": "2023-09-27 06:16:01", "rate1": 0, "rate7": -1}, {"fans": 971, "time": "2023-09-27 18:16:00", "rate1": 0, "rate7": -1}, {"fans": 971, "time": "2023-09-28 06:16:01", "rate1": 0, "rate7": -1}, {"fans": 971, "time": "2023-09-28 18:16:01", "rate1": 0, "rate7": -1}, {"fans": 971, "time": "2023-09-29 06:16:01", "rate1": 0, "rate7": -1}, {"fans": 972, "time": "2023-09-29 18:16:02", "rate1": 1, "rate7": 0}, {"fans": 972, "time": "2023-09-30 06:16:07", "rate1": 1, "rate7": 0}, {"fans": 971, "time": "2023-09-30 18:16:09", "rate1": -1, "rate7": 0}, {"fans": 971, "time": "2023-10-01 06:15:55", "rate1": -1, "rate7": 0}, {"fans": 971, "time": "2023-10-01 18:15:50", "rate1": 0, "rate7": 0}, {"fans": 971, "time": "2023-10-02 06:15:46", "rate1": 0, "rate7": 0}, {"fans": 971, "time": "2023-10-02 18:15:41", "rate1": 0, "rate7": 0}, {"fans": 971, "time": "2023-10-03 06:15:36", "rate1": 0, "rate7": 0}, {"fans": 971, "time": "2023-10-03 18:15:31", "rate1": 0, "rate7": 0}, {"fans": 971, "time": "2023-10-04 06:15:27", "rate1": 0, "rate7": 0}, {"fans": 971, "time": "2023-10-04 18:16:01", "rate1": 0, "rate7": 0}, {"fans": 971, "time": "2023-10-05 06:16:01", "rate1": 0, "rate7": 0}, {"fans": 971, "time": "2023-10-05 18:16:08", "rate1": 0, "rate7": 0}, {"fans": 971, "time": "2023-10-06 06:15:42", "rate1": 0, "rate7": 0}, {"fans": 971, "time": "2023-10-06 18:15:46", "rate1": 0, "rate7": -1}, {"fans": 971, "time": "2023-10-07 06:15:51", "rate1": 0, "rate7": -1}, {"fans": 971, "time": "2023-10-07 18:16:04", "rate1": 0, "rate7": 0}, {"fans": 971, "time": "2023-10-08 06:15:33", "rate1": 0, "rate7": 0}, {"fans": 971, "time": "2023-10-08 18:15:42", "rate1": 0, "rate7": 0}, {"fans": 971, "time": "2023-10-09 06:15:53", "rate1": 0, "rate7": 0}, {"fans": 971, "time": "2023-10-09 18:16:03", "rate1": 0, "rate7": 0}, {"fans": 971, "time": "2023-10-10 06:15:50", "rate1": 0, "rate7": 0}, {"fans": 971, "time": "2023-10-10 18:15:46", "rate1": 0, "rate7": 0}, {"fans": 971, "time": "2023-10-11 06:15:57", "rate1": 0, "rate7": 0}, {"fans": 971, "time": "2023-10-11 18:15:47", "rate1": 0, "rate7": 0}, {"fans": 971, "time": "2023-10-12 06:15:49", "rate1": 0, "rate7": 0}, {"fans": 971, "time": "2023-10-12 18:15:55", "rate1": 0, "rate7": 0}, {"fans": 971, "time": "2023-10-13 06:16:01", "rate1": 0, "rate7": 0}, {"fans": 971, "time": "2023-10-13 18:16:10", "rate1": 0, "rate7": 0}, {"fans": 971, "time": "2023-10-14 06:16:18", "rate1": 0, "rate7": 0}, {"fans": 971, "time": "2023-10-14 18:16:29", "rate1": 0, "rate7": 0}, {"fans": 971, "time": "2023-10-15 06:16:03", "rate1": 0, "rate7": 0}, {"fans": 969, "time": "2023-10-15 18:16:25", "rate1": -2, "rate7": -2}, {"fans": 969, "time": "2023-10-16 06:16:08", "rate1": -2, "rate7": -2}, {"fans": 969, "time": "2023-10-16 18:15:56", "rate1": 0, "rate7": -2}, {"fans": 969, "time": "2023-10-17 06:16:23", "rate1": 0, "rate7": -2}, {"fans": 968, "time": "2023-10-17 18:16:15", "rate1": -1, "rate7": -3}, {"fans": 968, "time": "2023-10-18 06:16:07", "rate1": -1, "rate7": -3}, {"fans": 968, "time": "2023-10-18 18:16:00", "rate1": 0, "rate7": -3}, {"fans": 969, "time": "2023-10-19 06:16:49", "rate1": 1, "rate7": -2}, {"fans": 968, "time": "2023-10-19 18:16:22", "rate1": 0, "rate7": -3}, {"fans": 967, "time": "2023-10-20 06:16:36", "rate1": -2, "rate7": -4}, {"fans": 967, "time": "2023-10-20 18:16:54", "rate1": -1, "rate7": -4}, {"fans": 967, "time": "2023-10-21 06:16:35", "rate1": 0, "rate7": -4}, {"fans": 967, "time": "2023-10-21 18:16:26", "rate1": 0, "rate7": -4}, {"fans": 967, "time": "2023-10-22 06:16:56", "rate1": 0, "rate7": -4}, {"fans": 966, "time": "2023-10-22 18:16:55", "rate1": -1, "rate7": -3}, {"fans": 966, "time": "2023-10-23 06:16:55", "rate1": -1, "rate7": -3}, {"fans": 966, "time": "2023-10-23 18:16:58", "rate1": 0, "rate7": -3}, {"fans": 966, "time": "2023-10-24 06:17:08", "rate1": 0, "rate7": -3}, {"fans": 966, "time": "2023-10-24 18:16:42", "rate1": 0, "rate7": -2}, {"fans": 966, "time": "2023-10-25 06:17:11", "rate1": 0, "rate7": -2}, {"fans": 966, "time": "2023-10-25 18:16:45", "rate1": 0, "rate7": -2}, {"fans": 966, "time": "2023-10-26 06:17:06", "rate1": 0, "rate7": -3}, {"fans": 966, "time": "2023-10-26 18:16:49", "rate1": 0, "rate7": -2}, {"fans": 966, "time": "2023-10-27 06:17:15", "rate1": 0, "rate7": -1}, {"fans": 966, "time": "2023-10-27 18:17:11", "rate1": 0, "rate7": -1}, {"fans": 966, "time": "2023-10-28 06:17:22", "rate1": 0, "rate7": -1}, {"fans": 966, "time": "2023-10-28 18:16:53", "rate1": 0, "rate7": -1}, {"fans": 966, "time": "2023-10-29 06:17:10", "rate1": 0, "rate7": -1}, {"fans": 965, "time": "2023-10-29 18:17:27", "rate1": -1, "rate7": -1}, {"fans": 965, "time": "2023-10-30 06:17:10", "rate1": -1, "rate7": -1}, {"fans": 965, "time": "2023-10-30 18:17:10", "rate1": 0, "rate7": -1}, {"fans": 965, "time": "2023-10-31 06:17:13", "rate1": 0, "rate7": -1}, {"fans": 964, "time": "2023-10-31 18:17:20", "rate1": -1, "rate7": -2}, {"fans": 964, "time": "2023-11-01 06:17:29", "rate1": -1, "rate7": -2}, {"fans": 964, "time": "2023-11-01 18:17:42", "rate1": 0, "rate7": -2}, {"fans": 964, "time": "2023-11-02 06:17:15", "rate1": 0, "rate7": -2}, {"fans": 964, "time": "2023-11-02 18:17:28", "rate1": 0, "rate7": -2}, {"fans": 964, "time": "2023-11-03 06:17:03", "rate1": 0, "rate7": -2}, {"fans": 964, "time": "2023-11-03 18:17:15", "rate1": 0, "rate7": -2}, {"fans": 964, "time": "2023-11-04 06:17:29", "rate1": 0, "rate7": -2}, {"fans": 964, "time": "2023-11-04 18:17:11", "rate1": 0, "rate7": -2}, {"fans": 964, "time": "2023-11-05 06:17:33", "rate1": 0, "rate7": -2}, {"fans": 964, "time": "2023-11-05 18:17:14", "rate1": 0, "rate7": -1}, {"fans": 964, "time": "2023-11-06 06:17:38", "rate1": 0, "rate7": -1}, {"fans": 964, "time": "2023-11-06 18:17:38", "rate1": 0, "rate7": -1}, {"fans": 964, "time": "2023-11-07 06:17:08", "rate1": 0, "rate7": -1}, {"fans": 964, "time": "2023-11-07 18:17:20", "rate1": 0, "rate7": 0}, {"fans": 964, "time": "2023-11-08 06:17:43", "rate1": 0, "rate7": 0}, {"fans": 964, "time": "2023-11-08 18:17:30", "rate1": 0, "rate7": 0}, {"fans": 964, "time": "2023-11-09 06:17:17", "rate1": 0, "rate7": 0}, {"fans": 964, "time": "2023-11-09 18:17:46", "rate1": 0, "rate7": 0}, {"fans": 964, "time": "2023-11-10 06:17:36", "rate1": 0, "rate7": 0}, {"fans": 964, "time": "2023-11-10 18:17:26", "rate1": 0, "rate7": 0}, {"fans": 964, "time": "2023-11-11 06:17:19", "rate1": 0, "rate7": 0}, {"fans": 964, "time": "2023-11-11 18:17:47", "rate1": 0, "rate7": 0}, {"fans": 964, "time": "2023-11-12 06:17:42", "rate1": 0, "rate7": 0}, {"fans": 964, "time": "2023-11-12 18:17:38", "rate1": 0, "rate7": 0}, {"fans": 964, "time": "2023-11-13 06:17:32", "rate1": 0, "rate7": 0}, {"fans": 964, "time": "2023-11-13 18:17:29", "rate1": 0, "rate7": 0}, {"fans": 964, "time": "2023-11-14 06:17:25", "rate1": 0, "rate7": 0}, {"fans": 964, "time": "2023-11-14 18:17:23", "rate1": 0, "rate7": 0}, {"fans": 964, "time": "2023-11-15 06:17:41", "rate1": 0, "rate7": 0}, {"fans": 964, "time": "2023-11-15 18:17:49", "rate1": 0, "rate7": 0}, {"fans": 964, "time": "2023-11-16 06:17:34", "rate1": 0, "rate7": 0}, {"fans": 963, "time": "2023-11-16 18:17:44", "rate1": -1, "rate7": -1}, {"fans": 963, "time": "2023-11-17 06:17:27", "rate1": -1, "rate7": -1}, {"fans": 963, "time": "2023-11-17 18:17:56", "rate1": 0, "rate7": -1}, {"fans": 963, "time": "2023-11-18 06:17:38", "rate1": 0, "rate7": -1}, {"fans": 963, "time": "2023-11-18 18:17:47", "rate1": 0, "rate7": -1}, {"fans": 963, "time": "2023-11-19 06:17:19", "rate1": 0, "rate7": -1}, {"fans": 963, "time": "2023-11-19 18:17:49", "rate1": 0, "rate7": -1}, {"fans": 963, "time": "2023-11-20 06:17:45", "rate1": 0, "rate7": -1}, {"fans": 963, "time": "2023-11-20 18:17:54", "rate1": 0, "rate7": -1}, {"fans": 963, "time": "2023-11-21 06:17:56", "rate1": 0, "rate7": -1}, {"fans": 963, "time": "2023-11-21 18:17:51", "rate1": 0, "rate7": -1}, {"fans": -1, "time": "2023-11-22 06:17:56", "rate1": -964, "rate7": -965}, {"fans": -1, "time": "2023-11-22 18:18:04", "rate1": -964, "rate7": -965}, {"fans": -1, "time": "2023-11-23 06:17:54", "rate1": 0, "rate7": -965}, {"fans": 961, "time": "2023-11-23 18:17:38", "rate1": 962, "rate7": -2}, {"fans": -1, "time": "2023-11-24 06:18:07", "rate1": 0, "rate7": -964}, {"fans": -1, "time": "2023-11-24 18:18:23", "rate1": -962, "rate7": -964}, {"fans": 961, "time": "2023-11-25 06:36:56", "rate1": 962, "rate7": -2}, {"fans": 961, "time": "2023-11-25 18:37:42", "rate1": 962, "rate7": -2}, {"fans": 961, "time": "2023-11-26 06:41:12", "rate1": 0, "rate7": -2}, {"fans": 961, "time": "2023-11-26 18:49:18", "rate1": 0, "rate7": -2}, {"fans": 961, "time": "2023-11-27 06:34:53", "rate1": 0, "rate7": -2}, {"fans": 961, "time": "2023-11-27 18:54:11", "rate1": 0, "rate7": -2}, {"fans": 961, "time": "2023-11-28 07:07:50", "rate1": 0, "rate7": -2}, {"fans": 961, "time": "2023-11-28 19:29:07", "rate1": 0, "rate7": -2}, {"fans": 961, "time": "2023-11-29 06:54:44", "rate1": 0, "rate7": 962}, {"fans": 961, "time": "2023-11-29 19:00:08", "rate1": 0, "rate7": 962}, {"fans": 961, "time": "2023-11-30 07:02:57", "rate1": 0, "rate7": 962}, {"fans": 961, "time": "2023-11-30 19:00:36", "rate1": 0, "rate7": 0}, {"fans": 961, "time": "2023-12-01 06:42:44", "rate1": 0, "rate7": 962}, {"fans": 961, "time": "2023-12-01 18:50:25", "rate1": 0, "rate7": 962}, {"fans": 961, "time": "2023-12-02 06:41:09", "rate1": 0, "rate7": 0}, {"fans": 961, "time": "2023-12-02 19:00:58", "rate1": 0, "rate7": 0}, {"fans": 960, "time": "2023-12-03 06:55:45", "rate1": -1, "rate7": -1}, {"fans": 960, "time": "2023-12-03 18:55:57", "rate1": -1, "rate7": -1}, {"fans": 960, "time": "2023-12-04 06:44:55", "rate1": 0, "rate7": -1}, {"fans": 960, "time": "2023-12-04 19:02:51", "rate1": 0, "rate7": -1}, {"fans": 960, "time": "2023-12-05 06:51:04", "rate1": 0, "rate7": -1}, {"fans": 960, "time": "2023-12-05 18:44:06", "rate1": 0, "rate7": -1}, {"fans": 960, "time": "2023-12-06 06:38:53", "rate1": 0, "rate7": -1}, {"fans": 960, "time": "2023-12-06 18:47:33", "rate1": 0, "rate7": -1}, {"fans": 960, "time": "2023-12-07 06:48:53", "rate1": 0, "rate7": -1}, {"fans": 960, "time": "2023-12-07 18:53:47", "rate1": 0, "rate7": -1}, {"fans": 961, "time": "2023-12-08 06:49:39", "rate1": 1, "rate7": 0}, {"fans": 961, "time": "2023-12-08 18:34:25", "rate1": 1, "rate7": 0}, {"fans": 961, "time": "2023-12-09 06:47:17", "rate1": 0, "rate7": 0}, {"fans": 960, "time": "2023-12-09 18:42:02", "rate1": -1, "rate7": -1}, {"fans": 960, "time": "2023-12-10 07:03:45", "rate1": -1, "rate7": 0}, {"fans": 960, "time": "2023-12-10 18:58:02", "rate1": 0, "rate7": 0}, {"fans": 960, "time": "2023-12-11 06:53:36", "rate1": 0, "rate7": 0}, {"fans": 960, "time": "2023-12-11 19:03:21", "rate1": 0, "rate7": 0}, {"fans": 960, "time": "2023-12-12 06:56:41", "rate1": 0, "rate7": 0}, {"fans": 960, "time": "2023-12-12 18:51:04", "rate1": 0, "rate7": 0}, {"fans": 960, "time": "2023-12-13 06:43:04", "rate1": 0, "rate7": 0}, {"fans": 960, "time": "2023-12-13 18:58:56", "rate1": 0, "rate7": 0}, {"fans": 960, "time": "2023-12-14 06:44:44", "rate1": 0, "rate7": 0}, {"fans": 960, "time": "2023-12-14 19:27:00", "rate1": 0, "rate7": 0}, {"fans": 960, "time": "2023-12-15 06:50:58", "rate1": 0, "rate7": -1}, {"fans": 960, "time": "2023-12-15 19:08:28", "rate1": 0, "rate7": -1}, {"fans": 959, "time": "2023-12-16 06:54:28", "rate1": -1, "rate7": -2}, {"fans": 959, "time": "2023-12-16 19:24:48", "rate1": -1, "rate7": -1}, {"fans": 959, "time": "2023-12-17 06:53:59", "rate1": 0, "rate7": -1}, {"fans": 959, "time": "2023-12-17 19:05:09", "rate1": 0, "rate7": -1}, {"fans": 959, "time": "2023-12-18 06:49:33", "rate1": 0, "rate7": -1}, {"fans": 959, "time": "2023-12-18 19:02:45", "rate1": 0, "rate7": -1}, {"fans": 959, "time": "2023-12-19 06:54:39", "rate1": 0, "rate7": -1}, {"fans": 959, "time": "2023-12-19 19:12:53", "rate1": 0, "rate7": -1}, {"fans": 959, "time": "2023-12-20 06:55:25", "rate1": 0, "rate7": -1}, {"fans": 959, "time": "2023-12-20 18:47:21", "rate1": 0, "rate7": -1}, {"fans": 959, "time": "2023-12-21 07:04:51", "rate1": 0, "rate7": -1}, {"fans": 959, "time": "2023-12-21 19:02:58", "rate1": 0, "rate7": -1}, {"fans": 959, "time": "2023-12-22 06:50:02", "rate1": 0, "rate7": -1}, {"fans": 959, "time": "2023-12-22 18:52:25", "rate1": 0, "rate7": -1}, {"fans": 959, "time": "2023-12-23 06:51:29", "rate1": 0, "rate7": 0}, {"fans": 959, "time": "2023-12-23 18:56:15", "rate1": 0, "rate7": 0}, {"fans": 959, "time": "2023-12-24 06:54:07", "rate1": 0, "rate7": 0}, {"fans": 959, "time": "2023-12-24 19:04:13", "rate1": 0, "rate7": 0}, {"fans": 959, "time": "2023-12-25 06:49:25", "rate1": 0, "rate7": 0}, {"fans": 959, "time": "2023-12-25 19:03:08", "rate1": 0, "rate7": 0}, {"fans": 959, "time": "2023-12-26 06:51:19", "rate1": 0, "rate7": 0}, {"fans": 959, "time": "2023-12-26 19:02:03", "rate1": 0, "rate7": 0}, {"fans": 960, "time": "2023-12-27 06:42:17", "rate1": 1, "rate7": 1}, {"fans": 960, "time": "2023-12-27 19:03:36", "rate1": 1, "rate7": 1}, {"fans": 960, "time": "2023-12-28 06:51:33", "rate1": 0, "rate7": 1}, {"fans": 960, "time": "2023-12-28 18:55:17", "rate1": 0, "rate7": 1}, {"fans": 960, "time": "2023-12-29 06:45:05", "rate1": 0, "rate7": 1}, {"fans": 960, "time": "2023-12-29 18:46:09", "rate1": 0, "rate7": 1}, {"fans": 960, "time": "2023-12-30 06:40:47", "rate1": 0, "rate7": 1}, {"fans": 960, "time": "2023-12-30 18:54:14", "rate1": 0, "rate7": 1}, {"fans": 960, "time": "2023-12-31 06:45:36", "rate1": 0, "rate7": 1}, {"fans": 960, "time": "2023-12-31 18:43:43", "rate1": 0, "rate7": 1}, {"fans": 960, "time": "2024-01-01 06:51:37", "rate1": 0, "rate7": 1}, {"fans": 960, "time": "2024-01-01 18:45:47", "rate1": 0, "rate7": 1}, {"fans": 960, "time": "2024-01-02 06:51:43", "rate1": 0, "rate7": 1}, {"fans": 960, "time": "2024-01-02 19:11:13", "rate1": 0, "rate7": 1}, {"fans": 960, "time": "2024-01-03 07:25:34", "rate1": 0, "rate7": 0}, {"fans": 960, "time": "2024-01-03 19:47:47", "rate1": -1, "rate7": -1}, {"fans": 960, "time": "2024-01-04 07:04:58", "rate1": 0, "rate7": 0}, {"fans": 960, "time": "2024-01-04 20:38:39", "rate1": 0, "rate7": 0}, {"fans": 960, "time": "2024-01-05 08:07:37", "rate1": 0, "rate7": 0}, {"fans": -1, "time": "2024-01-05 21:45:11", "rate1": -1, "rate7": -1}, {"fans": 960, "time": "2024-01-06 06:15:18", "rate1": 0, "rate7": 0}, {"fans": 960, "time": "2024-01-06 18:15:55", "rate1": 961, "rate7": 0}, {"fans": 960, "time": "2024-01-07 06:15:53", "rate1": 0, "rate7": 0}, {"fans": 959, "time": "2024-01-07 18:15:50", "rate1": -1, "rate7": -1}, {"fans": 960, "time": "2024-01-08 06:15:49", "rate1": 0, "rate7": 0}, {"fans": 960, "time": "2024-01-08 18:15:45", "rate1": 1, "rate7": 0}, {"fans": 960, "time": "2024-01-09 06:15:42", "rate1": 0, "rate7": 0}, {"fans": 960, "time": "2024-01-09 18:15:42", "rate1": 0, "rate7": 0}, {"fans": 960, "time": "2024-01-10 06:15:52", "rate1": 0, "rate7": 0}, {"fans": 960, "time": "2024-01-10 18:15:59", "rate1": 0, "rate7": 0}, {"fans": 960, "time": "2024-01-11 06:15:37", "rate1": 0, "rate7": 0}, {"fans": 960, "time": "2024-01-11 18:16:02", "rate1": 0, "rate7": 0}, {"fans": 959, "time": "2024-01-12 06:15:50", "rate1": -1, "rate7": -1}, {"fans": 959, "time": "2024-01-12 18:15:35", "rate1": -1, "rate7": 960}, {"fans": 959, "time": "2024-01-13 06:15:26", "rate1": 0, "rate7": -1}, {"fans": 959, "time": "2024-01-13 18:16:04", "rate1": 0, "rate7": -1}, {"fans": 959, "time": "2024-01-14 06:15:29", "rate1": 0, "rate7": -1}, {"fans": 959, "time": "2024-01-14 18:15:35", "rate1": 0, "rate7": 0}, {"fans": 959, "time": "2024-01-15 06:15:47", "rate1": 0, "rate7": -1}, {"fans": 959, "time": "2024-01-15 18:16:00", "rate1": 0, "rate7": -1}, {"fans": 959, "time": "2024-01-16 06:15:35", "rate1": 0, "rate7": -1}, {"fans": 959, "time": "2024-01-16 18:15:51", "rate1": 0, "rate7": -1}, {"fans": 959, "time": "2024-01-17 06:15:29", "rate1": 0, "rate7": -1}, {"fans": 959, "time": "2024-01-17 18:16:06", "rate1": 0, "rate7": -1}, {"fans": 959, "time": "2024-01-18 06:15:27", "rate1": 0, "rate7": -1}, {"fans": 959, "time": "2024-01-18 18:16:16", "rate1": 0, "rate7": -1}, {"fans": 959, "time": "2024-01-19 06:16:05", "rate1": 0, "rate7": 0}, {"fans": 959, "time": "2024-01-19 18:15:47", "rate1": 0, "rate7": 0}, {"fans": 959, "time": "2024-01-20 06:16:10", "rate1": 0, "rate7": 0}, {"fans": 959, "time": "2024-01-20 18:15:55", "rate1": 0, "rate7": 0}, {"fans": 959, "time": "2024-01-21 06:15:42", "rate1": 0, "rate7": 0}, {"fans": 959, "time": "2024-01-21 18:16:14", "rate1": 0, "rate7": 0}, {"fans": 959, "time": "2024-01-22 06:16:13", "rate1": 0, "rate7": 0}, {"fans": 959, "time": "2024-01-22 18:16:14", "rate1": 0, "rate7": 0}, {"fans": 960, "time": "2024-01-23 06:16:20", "rate1": 1, "rate7": 1}, {"fans": 960, "time": "2024-01-23 18:16:21", "rate1": 1, "rate7": 1}, {"fans": 960, "time": "2024-01-24 06:15:54", "rate1": 0, "rate7": 1}, {"fans": 960, "time": "2024-01-24 18:16:04", "rate1": 0, "rate7": 1}, {"fans": 959, "time": "2024-01-25 06:16:18", "rate1": -1, "rate7": 0}, {"fans": 959, "time": "2024-01-25 18:15:46", "rate1": -1, "rate7": 0}, {"fans": 958, "time": "2024-01-26 06:16:11", "rate1": -1, "rate7": -1}, {"fans": 958, "time": "2024-01-26 18:15:55", "rate1": -1, "rate7": -1}, {"fans": 958, "time": "2024-01-27 06:15:43", "rate1": 0, "rate7": -1}, {"fans": 958, "time": "2024-01-27 18:16:11", "rate1": 0, "rate7": -1}, {"fans": 958, "time": "2024-01-28 06:16:07", "rate1": 0, "rate7": -1}, {"fans": 958, "time": "2024-01-28 18:16:07", "rate1": 0, "rate7": -1}, {"fans": 958, "time": "2024-01-29 06:16:23", "rate1": 0, "rate7": -1}, {"fans": 958, "time": "2024-01-29 18:16:09", "rate1": 0, "rate7": -1}, {"fans": 958, "time": "2024-01-30 06:15:58", "rate1": 0, "rate7": -2}, {"fans": 958, "time": "2024-01-30 18:16:22", "rate1": 0, "rate7": -2}, {"fans": 958, "time": "2024-01-31 06:16:09", "rate1": 0, "rate7": -2}, {"fans": 958, "time": "2024-01-31 18:15:57", "rate1": 0, "rate7": -2}, {"fans": 958, "time": "2024-02-01 06:15:57", "rate1": 0, "rate7": -1}, {"fans": 958, "time": "2024-02-01 18:16:02", "rate1": 0, "rate7": -1}, {"fans": 958, "time": "2024-02-02 06:16:16", "rate1": 0, "rate7": 0}, {"fans": 958, "time": "2024-02-02 18:16:25", "rate1": 0, "rate7": 0}, {"fans": 958, "time": "2024-02-03 06:16:02", "rate1": 0, "rate7": 0}, {"fans": 958, "time": "2024-02-03 18:16:20", "rate1": 0, "rate7": 0}, {"fans": 958, "time": "2024-02-04 06:16:06", "rate1": 0, "rate7": 0}, {"fans": 958, "time": "2024-02-04 18:16:33", "rate1": 0, "rate7": 0}, {"fans": 958, "time": "2024-02-05 06:16:27", "rate1": 0, "rate7": 0}, {"fans": 958, "time": "2024-02-05 18:16:22", "rate1": 0, "rate7": 0}, {"fans": 958, "time": "2024-02-06 06:16:31", "rate1": 0, "rate7": 0}, {"fans": 958, "time": "2024-02-06 18:16:46", "rate1": 0, "rate7": 0}, {"fans": 958, "time": "2024-02-07 06:16:23", "rate1": 0, "rate7": 0}, {"fans": 958, "time": "2024-02-07 18:16:37", "rate1": 0, "rate7": 0}, {"fans": 958, "time": "2024-02-08 06:16:13", "rate1": 0, "rate7": 0}, {"fans": 958, "time": "2024-02-08 18:16:32", "rate1": 0, "rate7": 0}, {"fans": 957, "time": "2024-02-09 06:16:56", "rate1": -1, "rate7": -1}, {"fans": 957, "time": "2024-02-09 18:16:37", "rate1": -1, "rate7": -1}, {"fans": 957, "time": "2024-02-10 06:16:20", "rate1": 0, "rate7": -1}, {"fans": 957, "time": "2024-02-10 18:16:46", "rate1": 0, "rate7": -1}, {"fans": 957, "time": "2024-02-11 06:16:34", "rate1": 0, "rate7": -1}, {"fans": 956, "time": "2024-02-11 18:16:20", "rate1": -1, "rate7": -2}, {"fans": 956, "time": "2024-02-12 06:16:48", "rate1": -1, "rate7": -2}, {"fans": 956, "time": "2024-02-12 18:16:34", "rate1": 0, "rate7": -2}, {"fans": 956, "time": "2024-02-13 06:16:20", "rate1": 0, "rate7": -2}, {"fans": 956, "time": "2024-02-13 18:16:56", "rate1": 0, "rate7": -2}, {"fans": 956, "time": "2024-02-14 06:16:52", "rate1": 0, "rate7": -2}, {"fans": 956, "time": "2024-02-14 18:16:23", "rate1": 0, "rate7": -2}, {"fans": 956, "time": "2024-02-15 06:16:39", "rate1": 0, "rate7": -2}, {"fans": 956, "time": "2024-02-15 18:16:23", "rate1": 0, "rate7": -2}, {"fans": 956, "time": "2024-02-16 06:16:58", "rate1": 0, "rate7": -1}, {"fans": 956, "time": "2024-02-16 18:16:49", "rate1": 0, "rate7": -1}, {"fans": 956, "time": "2024-02-17 06:16:45", "rate1": 0, "rate7": -1}, {"fans": 956, "time": "2024-02-17 18:16:49", "rate1": 0, "rate7": -1}, {"fans": 956, "time": "2024-02-18 06:16:55", "rate1": 0, "rate7": -1}, {"fans": 955, "time": "2024-02-18 18:17:03", "rate1": -1, "rate7": -1}, {"fans": 955, "time": "2024-02-19 06:16:35", "rate1": -1, "rate7": -1}, {"fans": 955, "time": "2024-02-19 18:16:43", "rate1": 0, "rate7": -1}, {"fans": 955, "time": "2024-02-20 06:16:54", "rate1": 0, "rate7": -1}, {"fans": 955, "time": "2024-02-20 18:17:12", "rate1": 0, "rate7": -1}, {"fans": 955, "time": "2024-02-21 06:16:55", "rate1": 0, "rate7": -1}, {"fans": 955, "time": "2024-02-21 18:16:32", "rate1": 0, "rate7": -1}, {"fans": 955, "time": "2024-02-22 06:16:53", "rate1": 0, "rate7": -1}, {"fans": 955, "time": "2024-02-22 18:17:10", "rate1": 0, "rate7": -1}, {"fans": 955, "time": "2024-02-23 06:16:56", "rate1": 0, "rate7": -1}, {"fans": 955, "time": "2024-02-23 18:16:46", "rate1": 0, "rate7": -1}, {"fans": 955, "time": "2024-02-24 06:16:40", "rate1": 0, "rate7": -1}, {"fans": 954, "time": "2024-02-24 18:17:13", "rate1": -1, "rate7": -2}, {"fans": 954, "time": "2024-02-25 06:17:07", "rate1": -1, "rate7": -2}, {"fans": 954, "time": "2024-02-25 18:17:04", "rate1": 0, "rate7": -1}, {"fans": 954, "time": "2024-02-26 06:17:03", "rate1": 0, "rate7": -1}, {"fans": 954, "time": "2024-02-26 18:16:59", "rate1": 0, "rate7": -1}, {"fans": 954, "time": "2024-02-27 06:17:00", "rate1": 0, "rate7": -1}, {"fans": 953, "time": "2024-02-27 18:16:57", "rate1": -1, "rate7": -2}, {"fans": 953, "time": "2024-02-28 06:16:59", "rate1": -1, "rate7": -2}, {"fans": 953, "time": "2024-02-28 18:16:59", "rate1": 0, "rate7": -2}, {"fans": 953, "time": "2024-02-29 06:17:07", "rate1": 0, "rate7": -2}, {"fans": 953, "time": "2024-02-29 18:17:12", "rate1": 0, "rate7": -2}, {"fans": 953, "time": "2024-03-01 06:16:43", "rate1": 0, "rate7": -2}, {"fans": 953, "time": "2024-03-01 18:17:03", "rate1": 0, "rate7": -2}, {"fans": 953, "time": "2024-03-02 06:16:44", "rate1": 0, "rate7": -2}, {"fans": 953, "time": "2024-03-02 18:17:02", "rate1": 0, "rate7": -1}, {"fans": 953, "time": "2024-03-03 06:16:42", "rate1": 0, "rate7": -1}, {"fans": 953, "time": "2024-03-03 18:17:03", "rate1": 0, "rate7": -1}, {"fans": 953, "time": "2024-03-04 06:16:46", "rate1": 0, "rate7": -1}, {"fans": 953, "time": "2024-03-04 18:17:06", "rate1": 0, "rate7": -1}, {"fans": 953, "time": "2024-03-05 06:16:53", "rate1": 0, "rate7": -1}, {"fans": 953, "time": "2024-03-05 18:17:17", "rate1": 0, "rate7": 0}, {"fans": 953, "time": "2024-03-06 06:17:22", "rate1": 0, "rate7": 0}, {"fans": 953, "time": "2024-03-06 18:17:06", "rate1": 0, "rate7": 0}, {"fans": 953, "time": "2024-03-07 06:17:18", "rate1": 0, "rate7": 0}, {"fans": 953, "time": "2024-03-07 18:17:32", "rate1": 0, "rate7": 0}, {"fans": 953, "time": "2024-03-08 06:17:04", "rate1": 0, "rate7": 0}, {"fans": 953, "time": "2024-03-08 18:17:14", "rate1": 0, "rate7": 0}, {"fans": 953, "time": "2024-03-09 06:17:28", "rate1": 0, "rate7": 0}, {"fans": 953, "time": "2024-03-09 18:17:00", "rate1": 0, "rate7": 0}, {"fans": 953, "time": "2024-03-10 06:17:12", "rate1": 0, "rate7": 0}, {"fans": 953, "time": "2024-03-10 18:17:24", "rate1": 0, "rate7": 0}, {"fans": 953, "time": "2024-03-11 06:16:56", "rate1": 0, "rate7": 0}, {"fans": 953, "time": "2024-03-11 18:17:05", "rate1": 0, "rate7": 0}, {"fans": 953, "time": "2024-03-12 06:17:17", "rate1": 0, "rate7": 0}, {"fans": 953, "time": "2024-03-12 18:17:26", "rate1": 0, "rate7": 0}, {"fans": 953, "time": "2024-03-13 06:16:59", "rate1": 0, "rate7": 0}, {"fans": 953, "time": "2024-03-13 18:17:13", "rate1": 0, "rate7": 0}, {"fans": 953, "time": "2024-03-14 06:17:30", "rate1": 0, "rate7": 0}, {"fans": 953, "time": "2024-03-14 18:17:02", "rate1": 0, "rate7": 0}, {"fans": 953, "time": "2024-03-15 06:17:24", "rate1": 0, "rate7": 0}, {"fans": 953, "time": "2024-03-15 18:17:05", "rate1": 0, "rate7": 0}, {"fans": 953, "time": "2024-03-16 06:17:29", "rate1": 0, "rate7": 0}, {"fans": 953, "time": "2024-03-16 18:17:12", "rate1": 0, "rate7": 0}, {"fans": 953, "time": "2024-03-17 06:16:57", "rate1": 0, "rate7": 0}, {"fans": 953, "time": "2024-03-17 18:17:22", "rate1": 0, "rate7": 0}, {"fans": 952, "time": "2024-03-18 06:17:07", "rate1": -1, "rate7": -1}, {"fans": 952, "time": "2024-03-18 18:17:29", "rate1": -1, "rate7": -1}, {"fans": 952, "time": "2024-03-19 06:17:14", "rate1": 0, "rate7": -1}, {"fans": 952, "time": "2024-03-19 18:16:58", "rate1": 0, "rate7": -1}, {"fans": 952, "time": "2024-03-20 06:17:25", "rate1": 0, "rate7": -1}, {"fans": 952, "time": "2024-03-20 18:17:05", "rate1": 0, "rate7": -1}, {"fans": 952, "time": "2024-03-21 06:17:31", "rate1": 0, "rate7": -1}, {"fans": 952, "time": "2024-03-21 18:17:16", "rate1": 0, "rate7": -1}, {"fans": 952, "time": "2024-03-22 06:17:04", "rate1": 0, "rate7": -1}, {"fans": 952, "time": "2024-03-22 18:17:34", "rate1": 0, "rate7": -1}, {"fans": 952, "time": "2024-03-23 06:17:22", "rate1": 0, "rate7": -1}, {"fans": 952, "time": "2024-03-23 18:17:12", "rate1": 0, "rate7": -1}, {"fans": 952, "time": "2024-03-24 06:17:09", "rate1": 0, "rate7": -1}, {"fans": 951, "time": "2024-03-24 18:17:01", "rate1": -1, "rate7": -2}, {"fans": 951, "time": "2024-03-25 06:17:34", "rate1": -1, "rate7": -1}, {"fans": 951, "time": "2024-03-25 18:17:31", "rate1": 0, "rate7": -1}, {"fans": 951, "time": "2024-03-26 06:17:27", "rate1": 0, "rate7": -1}, {"fans": 951, "time": "2024-03-26 18:17:21", "rate1": 0, "rate7": -1}, {"fans": 950, "time": "2024-03-27 06:17:18", "rate1": -1, "rate7": -2}, {"fans": 950, "time": "2024-03-27 18:17:12", "rate1": -1, "rate7": -2}, {"fans": 950, "time": "2024-03-28 06:17:14", "rate1": 0, "rate7": -2}, {"fans": 950, "time": "2024-03-28 18:17:15", "rate1": 0, "rate7": -2}, {"fans": 950, "time": "2024-03-29 06:17:17", "rate1": 0, "rate7": -2}, {"fans": 950, "time": "2024-03-29 18:17:18", "rate1": 0, "rate7": -2}, {"fans": 950, "time": "2024-03-30 06:17:22", "rate1": 0, "rate7": -2}, {"fans": 950, "time": "2024-03-30 18:17:25", "rate1": 0, "rate7": -2}, {"fans": 950, "time": "2024-03-31 06:17:32", "rate1": 0, "rate7": -2}, {"fans": 950, "time": "2024-03-31 18:17:37", "rate1": 0, "rate7": -1}, {"fans": 949, "time": "2024-04-01 06:17:08", "rate1": -1, "rate7": -2}, {"fans": 949, "time": "2024-04-01 18:17:19", "rate1": -1, "rate7": -2}, {"fans": 949, "time": "2024-04-02 06:17:27", "rate1": 0, "rate7": -2}, {"fans": 949, "time": "2024-04-02 18:17:35", "rate1": 0, "rate7": -2}, {"fans": 949, "time": "2024-04-03 06:17:41", "rate1": 0, "rate7": -1}, {"fans": 949, "time": "2024-04-03 18:17:13", "rate1": 0, "rate7": -1}, {"fans": 949, "time": "2024-04-04 06:17:26", "rate1": 0, "rate7": -1}, {"fans": 949, "time": "2024-04-04 18:17:38", "rate1": 0, "rate7": -1}, {"fans": 949, "time": "2024-04-05 06:17:14", "rate1": 0, "rate7": -1}, {"fans": 948, "time": "2024-04-05 18:17:30", "rate1": -1, "rate7": -2}, {"fans": 948, "time": "2024-04-06 06:17:06", "rate1": -1, "rate7": -2}, {"fans": 948, "time": "2024-04-06 18:17:23", "rate1": 0, "rate7": -2}, {"fans": 948, "time": "2024-04-07 06:17:45", "rate1": 0, "rate7": -2}, {"fans": 948, "time": "2024-04-07 18:17:21", "rate1": 0, "rate7": -2}, {"fans": 948, "time": "2024-04-08 06:17:41", "rate1": 0, "rate7": -1}, {"fans": 948, "time": "2024-04-08 18:17:19", "rate1": 0, "rate7": -1}, {"fans": 948, "time": "2024-04-09 06:17:37", "rate1": 0, "rate7": -1}, {"fans": 948, "time": "2024-04-09 18:17:13", "rate1": 0, "rate7": -1}, {"fans": 947, "time": "2024-04-10 06:17:30", "rate1": -1, "rate7": -2}, {"fans": 947, "time": "2024-04-10 18:17:06", "rate1": -1, "rate7": -2}, {"fans": 947, "time": "2024-04-11 06:17:26", "rate1": 0, "rate7": -2}, {"fans": 947, "time": "2024-04-11 18:17:38", "rate1": 0, "rate7": -2}, {"fans": 947, "time": "2024-04-12 06:17:16", "rate1": 0, "rate7": -2}, {"fans": 947, "time": "2024-04-12 18:17:32", "rate1": 0, "rate7": -1}, {"fans": 948, "time": "2024-04-13 06:17:11", "rate1": 1, "rate7": 0}, {"fans": 948, "time": "2024-04-13 18:17:32", "rate1": 1, "rate7": 0}, {"fans": 948, "time": "2024-04-14 06:17:14", "rate1": 0, "rate7": 0}, {"fans": 948, "time": "2024-04-14 18:17:28", "rate1": 0, "rate7": 0}, {"fans": 948, "time": "2024-04-15 06:17:08", "rate1": 0, "rate7": 0}, {"fans": 948, "time": "2024-04-15 18:17:31", "rate1": 0, "rate7": 0}, {"fans": 948, "time": "2024-04-16 06:17:18", "rate1": 0, "rate7": 0}, {"fans": 948, "time": "2024-04-16 18:17:42", "rate1": 0, "rate7": 0}, {"fans": 948, "time": "2024-04-17 06:17:29", "rate1": 0, "rate7": 1}, {"fans": 948, "time": "2024-04-17 18:17:11", "rate1": 0, "rate7": 1}, {"fans": 946, "time": "2024-04-18 06:17:40", "rate1": -2, "rate7": -1}, {"fans": 946, "time": "2024-04-18 18:17:36", "rate1": -2, "rate7": -1}, {"fans": 946, "time": "2024-04-19 06:17:42", "rate1": 0, "rate7": -1}, {"fans": 946, "time": "2024-04-19 18:17:29", "rate1": 0, "rate7": -1}, {"fans": 946, "time": "2024-04-20 06:17:45", "rate1": 0, "rate7": -2}, {"fans": 945, "time": "2024-04-20 18:17:42", "rate1": -1, "rate7": -3}, {"fans": 945, "time": "2024-04-21 06:17:45", "rate1": -1, "rate7": -3}, {"fans": 945, "time": "2024-04-21 18:17:41", "rate1": 0, "rate7": -3}, {"fans": 945, "time": "2024-04-22 06:17:57", "rate1": 0, "rate7": -3}, {"fans": 945, "time": "2024-04-22 18:17:51", "rate1": 0, "rate7": -3}, {"fans": 945, "time": "2024-04-23 06:17:43", "rate1": 0, "rate7": -3}, {"fans": 945, "time": "2024-04-23 18:17:46", "rate1": 0, "rate7": -3}, {"fans": 945, "time": "2024-04-24 06:17:51", "rate1": 0, "rate7": -3}, {"fans": 945, "time": "2024-04-24 18:17:18", "rate1": 0, "rate7": -3}, {"fans": 945, "time": "2024-04-25 06:17:32", "rate1": 0, "rate7": -1}, {"fans": 945, "time": "2024-04-25 18:17:42", "rate1": 0, "rate7": -1}, {"fans": 945, "time": "2024-04-26 06:17:16", "rate1": 0, "rate7": -1}, {"fans": 945, "time": "2024-04-26 18:17:30", "rate1": 0, "rate7": -1}, {"fans": 945, "time": "2024-04-27 06:17:48", "rate1": 0, "rate7": -1}, {"fans": 945, "time": "2024-04-27 18:17:22", "rate1": 0, "rate7": 0}, {"fans": 945, "time": "2024-04-28 06:17:38", "rate1": 0, "rate7": 0}, {"fans": 945, "time": "2024-04-28 18:17:14", "rate1": 0, "rate7": 0}, {"fans": 944, "time": "2024-04-29 06:17:32", "rate1": -1, "rate7": -1}, {"fans": 944, "time": "2024-04-29 18:17:47", "rate1": -1, "rate7": -1}, {"fans": 944, "time": "2024-04-30 06:17:24", "rate1": 0, "rate7": -1}, {"fans": 944, "time": "2024-04-30 18:17:37", "rate1": 0, "rate7": -1}, {"fans": 944, "time": "2024-05-01 06:17:53", "rate1": 0, "rate7": -1}, {"fans": 944, "time": "2024-05-01 18:17:29", "rate1": 0, "rate7": -1}, {"fans": 944, "time": "2024-05-02 06:17:46", "rate1": 0, "rate7": -1}, {"fans": 944, "time": "2024-05-02 18:17:21", "rate1": 0, "rate7": -1}, {"fans": 944, "time": "2024-05-03 06:17:40", "rate1": 0, "rate7": -1}, {"fans": 944, "time": "2024-05-03 18:17:58", "rate1": 0, "rate7": -1}, {"fans": 944, "time": "2024-05-04 06:17:41", "rate1": 0, "rate7": -1}, {"fans": 944, "time": "2024-05-04 18:17:17", "rate1": 0, "rate7": -1}, {"fans": 944, "time": "2024-05-05 06:17:38", "rate1": 0, "rate7": -1}, {"fans": 944, "time": "2024-05-05 18:17:54", "rate1": 0, "rate7": -1}, {"fans": 944, "time": "2024-05-06 06:17:31", "rate1": 0, "rate7": 0}, {"fans": 944, "time": "2024-05-06 18:17:46", "rate1": 0, "rate7": 0}, {"fans": 944, "time": "2024-05-07 06:17:24", "rate1": 0, "rate7": 0}, {"fans": 944, "time": "2024-05-07 18:17:39", "rate1": 0, "rate7": 0}, {"fans": 944, "time": "2024-05-08 06:17:16", "rate1": 0, "rate7": 0}, {"fans": 944, "time": "2024-05-08 18:17:28", "rate1": 0, "rate7": 0}, {"fans": 944, "time": "2024-05-09 06:17:44", "rate1": 0, "rate7": 0}, {"fans": 944, "time": "2024-05-09 18:17:16", "rate1": 0, "rate7": 0}, {"fans": 944, "time": "2024-05-10 06:17:31", "rate1": 0, "rate7": 0}, {"fans": 944, "time": "2024-05-10 18:17:47", "rate1": 0, "rate7": 0}, {"fans": 944, "time": "2024-05-11 06:17:25", "rate1": 0, "rate7": 0}, {"fans": 944, "time": "2024-05-11 18:17:37", "rate1": 0, "rate7": 0}, {"fans": 943, "time": "2024-05-12 06:17:18", "rate1": -1, "rate7": -1}, {"fans": 943, "time": "2024-05-12 18:17:34", "rate1": -1, "rate7": -1}, {"fans": 943, "time": "2024-05-13 06:17:14", "rate1": 0, "rate7": -1}, {"fans": 943, "time": "2024-05-13 18:17:28", "rate1": 0, "rate7": -1}, {"fans": 943, "time": "2024-05-14 06:17:55", "rate1": 0, "rate7": -1}, {"fans": 943, "time": "2024-05-14 18:17:38", "rate1": 0, "rate7": -1}, {"fans": 943, "time": "2024-05-15 06:17:24", "rate1": 0, "rate7": -1}, {"fans": 943, "time": "2024-05-15 18:17:53", "rate1": 0, "rate7": -1}, {"fans": 943, "time": "2024-05-16 06:17:42", "rate1": 0, "rate7": -1}, {"fans": 943, "time": "2024-05-16 18:17:32", "rate1": 0, "rate7": -1}, {"fans": 943, "time": "2024-05-17 06:17:23", "rate1": 0, "rate7": -1}, {"fans": 943, "time": "2024-05-17 18:17:56", "rate1": 0, "rate7": -1}, {"fans": 943, "time": "2024-05-18 06:17:50", "rate1": 0, "rate7": -1}, {"fans": 943, "time": "2024-05-18 18:17:47", "rate1": 0, "rate7": -1}, {"fans": 943, "time": "2024-05-19 18:17:59", "rate1": 0, "rate7": 0}, {"fans": 943, "time": "2024-05-20 06:17:59", "rate1": 0, "rate7": 0}, {"fans": 943, "time": "2024-05-20 18:17:54", "rate1": 0, "rate7": 0}, {"fans": 943, "time": "2024-05-21 06:17:55", "rate1": 0, "rate7": 0}, {"fans": 943, "time": "2024-05-21 18:17:53", "rate1": 0, "rate7": 0}, {"fans": 943, "time": "2024-05-22 06:17:50", "rate1": 0, "rate7": 0}, {"fans": 943, "time": "2024-05-22 18:17:49", "rate1": 0, "rate7": 0}, {"fans": 943, "time": "2024-05-23 06:17:54", "rate1": 0, "rate7": 0}, {"fans": 943, "time": "2024-05-23 18:17:54", "rate1": 0, "rate7": 0}, {"fans": 943, "time": "2024-05-24 06:17:59", "rate1": 0, "rate7": 0}, {"fans": 943, "time": "2024-05-24 18:17:21", "rate1": 0, "rate7": 0}, {"fans": 943, "time": "2024-05-25 06:17:23", "rate1": 0, "rate7": 0}, {"fans": 943, "time": "2024-05-25 18:17:27", "rate1": 0, "rate7": 0}, {"fans": 944, "time": "2024-05-26 06:17:38", "rate1": 1, "rate7": 1}, {"fans": 944, "time": "2024-05-26 18:17:45", "rate1": 1, "rate7": 1}, {"fans": 944, "time": "2024-05-27 06:17:55", "rate1": 0, "rate7": 1}, {"fans": 944, "time": "2024-05-27 18:17:30", "rate1": 0, "rate7": 1}, {"fans": 944, "time": "2024-05-28 06:17:37", "rate1": 0, "rate7": 1}, {"fans": 944, "time": "2024-05-28 18:17:44", "rate1": 0, "rate7": 1}, {"fans": 944, "time": "2024-05-29 06:17:59", "rate1": 0, "rate7": 1}, {"fans": 944, "time": "2024-05-29 18:17:33", "rate1": 0, "rate7": 1}, {"fans": 944, "time": "2024-05-30 18:17:49", "rate1": 0, "rate7": 1}, {"fans": 944, "time": "2024-05-31 06:18:08", "rate1": 0, "rate7": 1}, {"fans": 944, "time": "2024-05-31 18:17:47", "rate1": 0, "rate7": 1}, {"fans": 944, "time": "2024-06-01 06:18:01", "rate1": 0, "rate7": 1}, {"fans": 944, "time": "2024-06-01 18:17:35", "rate1": 0, "rate7": 1}, {"fans": 944, "time": "2024-06-02 06:17:51", "rate1": 0, "rate7": 1}, {"fans": 944, "time": "2024-06-02 18:17:32", "rate1": 0, "rate7": 0}, {"fans": 944, "time": "2024-06-03 06:17:53", "rate1": 0, "rate7": 0}, {"fans": 944, "time": "2024-06-03 18:17:34", "rate1": 0, "rate7": 0}, {"fans": 944, "time": "2024-06-04 06:17:52", "rate1": 0, "rate7": 0}, {"fans": 944, "time": "2024-06-04 18:17:37", "rate1": 0, "rate7": 0}, {"fans": 944, "time": "2024-06-05 06:18:04", "rate1": 0, "rate7": 0}, {"fans": 944, "time": "2024-06-05 18:17:48", "rate1": 0, "rate7": 0}, {"fans": 944, "time": "2024-06-06 06:17:34", "rate1": 0, "rate7": 0}, {"fans": 944, "time": "2024-06-06 18:17:58", "rate1": 0, "rate7": 0}, {"fans": 944, "time": "2024-06-07 06:17:47", "rate1": 0, "rate7": 0}, {"fans": 945, "time": "2024-06-07 18:17:35", "rate1": 1, "rate7": 1}, {"fans": 945, "time": "2024-06-08 06:18:05", "rate1": 1, "rate7": 1}, {"fans": 945, "time": "2024-06-08 18:18:01", "rate1": 0, "rate7": 1}, {"fans": 945, "time": "2024-06-09 06:18:03", "rate1": 0, "rate7": 1}, {"fans": 945, "time": "2024-06-09 18:18:07", "rate1": 0, "rate7": 1}, {"fans": 945, "time": "2024-06-10 06:17:41", "rate1": 0, "rate7": 1}, {"fans": 945, "time": "2024-06-10 18:17:52", "rate1": 0, "rate7": 1}, {"fans": 945, "time": "2024-06-11 06:18:06", "rate1": 0, "rate7": 1}, {"fans": 945, "time": "2024-06-11 18:17:47", "rate1": 0, "rate7": 1}, {"fans": 945, "time": "2024-06-12 06:18:11", "rate1": 0, "rate7": 1}, {"fans": 945, "time": "2024-06-12 18:17:48", "rate1": 0, "rate7": 1}, {"fans": 945, "time": "2024-06-13 06:17:37", "rate1": 0, "rate7": 1}, {"fans": 945, "time": "2024-06-13 18:18:13", "rate1": 0, "rate7": 1}, {"fans": 945, "time": "2024-06-14 06:18:11", "rate1": 0, "rate7": 1}, {"fans": 945, "time": "2024-06-14 18:18:06", "rate1": 0, "rate7": 0}, {"fans": 945, "time": "2024-06-15 06:17:33", "rate1": 0, "rate7": 0}, {"fans": 945, "time": "2024-06-15 18:17:41", "rate1": 0, "rate7": 0}, {"fans": 945, "time": "2024-06-16 06:17:49", "rate1": 0, "rate7": 0}, {"fans": 945, "time": "2024-06-16 18:18:02", "rate1": 0, "rate7": 0}, {"fans": 944, "time": "2024-06-17 06:17:40", "rate1": -1, "rate7": -1}, {"fans": 944, "time": "2024-06-17 18:17:58", "rate1": -1, "rate7": -1}, {"fans": 944, "time": "2024-06-18 06:17:39", "rate1": 0, "rate7": -1}, {"fans": 945, "time": "2024-06-18 18:18:04", "rate1": 1, "rate7": 0}, {"fans": 945, "time": "2024-06-19 06:17:48", "rate1": 1, "rate7": 0}, {"fans": 945, "time": "2024-06-19 18:18:10", "rate1": 0, "rate7": 0}, {"fans": 945, "time": "2024-06-20 06:17:52", "rate1": 0, "rate7": 0}, {"fans": 945, "time": "2024-06-20 18:18:13", "rate1": 0, "rate7": 0}, {"fans": 945, "time": "2024-06-21 06:17:56", "rate1": 0, "rate7": 0}, {"fans": 945, "time": "2024-06-21 18:18:18", "rate1": 0, "rate7": 0}, {"fans": 945, "time": "2024-06-22 06:18:05", "rate1": 0, "rate7": 0}, {"fans": 945, "time": "2024-06-22 18:18:05", "rate1": 0, "rate7": 0}, {"fans": 945, "time": "2024-06-23 06:18:07", "rate1": 0, "rate7": 0}, {"fans": 945, "time": "2024-06-23 18:18:14", "rate1": 0, "rate7": 0}, {"fans": 945, "time": "2024-06-24 06:17:43", "rate1": 0, "rate7": 1}, {"fans": 945, "time": "2024-06-24 18:17:53", "rate1": 0, "rate7": 1}, {"fans": 945, "time": "2024-06-25 06:18:11", "rate1": 0, "rate7": 1}, {"fans": 945, "time": "2024-06-25 18:17:52", "rate1": 0, "rate7": 0}, {"fans": 945, "time": "2024-06-26 06:18:14", "rate1": 0, "rate7": 0}, {"fans": 945, "time": "2024-06-26 18:18:17", "rate1": 0, "rate7": 0}, {"fans": 945, "time": "2024-06-27 06:17:50", "rate1": 0, "rate7": 0}, {"fans": 945, "time": "2024-06-27 18:17:57", "rate1": 0, "rate7": 0}, {"fans": 945, "time": "2024-06-28 06:18:18", "rate1": 0, "rate7": 0}, {"fans": 945, "time": "2024-06-28 18:17:57", "rate1": 0, "rate7": 0}, {"fans": 945, "time": "2024-06-29 06:17:45", "rate1": 0, "rate7": 0}, {"fans": 945, "time": "2024-06-29 18:18:06", "rate1": 0, "rate7": 0}, {"fans": 945, "time": "2024-06-30 06:17:50", "rate1": 0, "rate7": 0}, {"fans": 945, "time": "2024-06-30 18:18:15", "rate1": 0, "rate7": 0}, {"fans": 945, "time": "2024-07-01 06:18:01", "rate1": 0, "rate7": 0}, {"fans": 945, "time": "2024-07-01 18:17:52", "rate1": 0, "rate7": 0}, {"fans": 945, "time": "2024-07-02 06:17:50", "rate1": 0, "rate7": 0}, {"fans": 945, "time": "2024-07-02 18:18:20", "rate1": 0, "rate7": 0}, {"fans": 945, "time": "2024-07-03 06:18:12", "rate1": 0, "rate7": 0}, {"fans": 945, "time": "2024-07-03 18:18:04", "rate1": 0, "rate7": 0}, {"fans": 945, "time": "2024-07-04 06:18:01", "rate1": 0, "rate7": 0}, {"fans": 945, "time": "2024-07-04 18:18:06", "rate1": 0, "rate7": 0}, {"fans": 945, "time": "2024-07-05 06:18:25", "rate1": 0, "rate7": 0}, {"fans": 945, "time": "2024-07-05 18:18:28", "rate1": 0, "rate7": 0}, {"fans": 945, "time": "2024-07-06 06:17:55", "rate1": 0, "rate7": 0}, {"fans": 945, "time": "2024-07-06 18:18:04", "rate1": 0, "rate7": 0}, {"fans": 945, "time": "2024-07-07 06:18:19", "rate1": 0, "rate7": 0}, {"fans": 944, "time": "2024-07-07 18:18:29", "rate1": -1, "rate7": -1}, {"fans": 944, "time": "2024-07-08 06:18:03", "rate1": -1, "rate7": -1}, {"fans": 944, "time": "2024-07-08 18:18:23", "rate1": 0, "rate7": -1}, {"fans": 944, "time": "2024-07-09 06:18:06", "rate1": 0, "rate7": -1}, {"fans": 943, "time": "2024-07-09 18:18:13", "rate1": -1, "rate7": -2}, {"fans": 943, "time": "2024-07-10 06:18:23", "rate1": -1, "rate7": -2}, {"fans": 943, "time": "2024-07-10 18:18:31", "rate1": 0, "rate7": -2}, {"fans": 943, "time": "2024-07-11 06:18:15", "rate1": 0, "rate7": -2}, {"fans": 943, "time": "2024-07-11 18:17:56", "rate1": 0, "rate7": -2}, {"fans": 943, "time": "2024-07-12 06:18:25", "rate1": 0, "rate7": -2}, {"fans": 943, "time": "2024-07-12 18:18:08", "rate1": 0, "rate7": -2}, {"fans": 943, "time": "2024-07-13 06:18:38", "rate1": 0, "rate7": -2}, {"fans": 943, "time": "2024-07-13 18:18:25", "rate1": 0, "rate7": -2}, {"fans": 943, "time": "2024-07-14 06:18:12", "rate1": 0, "rate7": -2}, {"fans": 943, "time": "2024-07-14 18:18:05", "rate1": 0, "rate7": -1}, {"fans": 943, "time": "2024-07-15 06:18:06", "rate1": 0, "rate7": -1}, {"fans": 943, "time": "2024-07-15 18:18:05", "rate1": 0, "rate7": -1}, {"fans": 942, "time": "2024-07-16 06:18:12", "rate1": -1, "rate7": -2}, {"fans": 942, "time": "2024-07-16 18:18:21", "rate1": -1, "rate7": -1}, {"fans": 942, "time": "2024-07-17 06:18:37", "rate1": 0, "rate7": -1}, {"fans": 942, "time": "2024-07-17 18:18:12", "rate1": 0, "rate7": -1}, {"fans": 942, "time": "2024-07-18 06:18:33", "rate1": 0, "rate7": -1}, {"fans": 942, "time": "2024-07-18 18:18:15", "rate1": 0, "rate7": -1}, {"fans": 942, "time": "2024-07-19 06:18:44", "rate1": 0, "rate7": -1}, {"fans": 942, "time": "2024-07-19 18:18:24", "rate1": 0, "rate7": -1}, {"fans": 942, "time": "2024-07-20 06:18:08", "rate1": 0, "rate7": -1}, {"fans": 942, "time": "2024-07-20 18:18:31", "rate1": 0, "rate7": -1}, {"fans": 942, "time": "2024-07-21 06:18:17", "rate1": 0, "rate7": -1}, {"fans": 942, "time": "2024-07-21 18:18:12", "rate1": 0, "rate7": -1}, {"fans": 942, "time": "2024-07-22 06:18:10", "rate1": 0, "rate7": -1}, {"fans": 941, "time": "2024-07-22 18:18:42", "rate1": -1, "rate7": -2}, {"fans": 941, "time": "2024-07-23 06:18:35", "rate1": -1, "rate7": -1}, {"fans": 941, "time": "2024-07-23 18:18:36", "rate1": 0, "rate7": -1}, {"fans": 941, "time": "2024-07-24 06:18:09", "rate1": 0, "rate7": -1}, {"fans": 941, "time": "2024-07-24 18:18:27", "rate1": 0, "rate7": -1}, {"fans": 941, "time": "2024-07-25 06:18:13", "rate1": 0, "rate7": -1}, {"fans": 941, "time": "2024-07-25 18:18:51", "rate1": 0, "rate7": -1}, {"fans": 941, "time": "2024-07-26 06:18:20", "rate1": 0, "rate7": -1}, {"fans": 942, "time": "2024-07-26 18:18:27", "rate1": 1, "rate7": 0}, {"fans": 942, "time": "2024-07-27 06:18:45", "rate1": 1, "rate7": 0}, {"fans": 942, "time": "2024-07-27 18:18:23", "rate1": 0, "rate7": 0}, {"fans": 942, "time": "2024-07-28 06:18:50", "rate1": 0, "rate7": 0}, {"fans": 941, "time": "2024-07-28 18:18:33", "rate1": -1, "rate7": -1}, {"fans": 941, "time": "2024-07-29 06:18:17", "rate1": -1, "rate7": -1}, {"fans": 941, "time": "2024-07-29 18:18:37", "rate1": 0, "rate7": 0}, {"fans": 941, "time": "2024-07-30 06:18:24", "rate1": 0, "rate7": 0}, {"fans": 941, "time": "2024-07-30 18:18:54", "rate1": 0, "rate7": 0}, {"fans": 941, "time": "2024-07-31 06:18:42", "rate1": 0, "rate7": 0}, {"fans": 941, "time": "2024-07-31 18:18:19", "rate1": 0, "rate7": 0}, {"fans": 941, "time": "2024-08-01 06:18:18", "rate1": 0, "rate7": 0}, {"fans": 941, "time": "2024-08-01 18:18:54", "rate1": 0, "rate7": 0}, {"fans": 941, "time": "2024-08-02 06:18:50", "rate1": 0, "rate7": 0}, {"fans": 941, "time": "2024-08-02 18:18:46", "rate1": 0, "rate7": -1}, {"fans": 941, "time": "2024-08-03 06:18:44", "rate1": 0, "rate7": -1}, {"fans": 941, "time": "2024-08-03 18:18:39", "rate1": 0, "rate7": -1}, {"fans": 941, "time": "2024-08-04 06:18:48", "rate1": 0, "rate7": -1}, {"fans": 941, "time": "2024-08-04 18:18:49", "rate1": 0, "rate7": 0}, {"fans": 941, "time": "2024-08-05 06:18:20", "rate1": 0, "rate7": 0}, {"fans": 941, "time": "2024-08-05 18:18:23", "rate1": 0, "rate7": 0}, {"fans": 941, "time": "2024-08-06 06:18:38", "rate1": 0, "rate7": 0}, {"fans": 941, "time": "2024-08-06 18:18:53", "rate1": 0, "rate7": 0}, {"fans": 941, "time": "2024-08-07 06:18:39", "rate1": 0, "rate7": 0}, {"fans": 941, "time": "2024-08-07 18:18:22", "rate1": 0, "rate7": 0}, {"fans": 940, "time": "2024-08-08 06:18:20", "rate1": -1, "rate7": -1}, {"fans": 940, "time": "2024-08-08 18:18:53", "rate1": -1, "rate7": -1}, {"fans": 940, "time": "2024-08-09 06:18:49", "rate1": 0, "rate7": -1}, {"fans": 940, "time": "2024-08-09 18:18:42", "rate1": 0, "rate7": -1}, {"fans": 938, "time": "2024-08-10 06:18:39", "rate1": -2, "rate7": -3}, {"fans": 938, "time": "2024-08-10 18:18:40", "rate1": -2, "rate7": -3}, {"fans": 938, "time": "2024-08-11 06:18:45", "rate1": 0, "rate7": -3}, {"fans": 938, "time": "2024-08-11 18:18:43", "rate1": 0, "rate7": -3}, {"fans": 938, "time": "2024-08-12 06:18:49", "rate1": 0, "rate7": -3}, {"fans": 938, "time": "2024-08-12 18:18:49", "rate1": 0, "rate7": -3}, {"fans": 938, "time": "2024-08-13 06:18:15", "rate1": 0, "rate7": -3}, {"fans": 938, "time": "2024-08-13 18:18:57", "rate1": 0, "rate7": -3}, {"fans": 938, "time": "2024-08-14 06:18:25", "rate1": 0, "rate7": -3}, {"fans": 938, "time": "2024-08-14 18:18:33", "rate1": 0, "rate7": -3}, {"fans": 938, "time": "2024-08-15 06:18:44", "rate1": 0, "rate7": -2}, {"fans": 937, "time": "2024-08-15 18:18:53", "rate1": -1, "rate7": -3}, {"fans": 936, "time": "2024-08-16 06:18:27", "rate1": -2, "rate7": -4}, {"fans": 936, "time": "2024-08-16 18:18:44", "rate1": -1, "rate7": -4}, {"fans": 936, "time": "2024-08-17 06:18:27", "rate1": 0, "rate7": -2}, {"fans": 936, "time": "2024-08-17 18:18:48", "rate1": 0, "rate7": -2}, {"fans": 936, "time": "2024-08-18 06:18:36", "rate1": 0, "rate7": -2}, {"fans": 936, "time": "2024-08-18 18:18:19", "rate1": 0, "rate7": -2}, {"fans": 936, "time": "2024-08-19 06:18:47", "rate1": 0, "rate7": -2}, {"fans": 936, "time": "2024-08-19 18:18:42", "rate1": 0, "rate7": -2}, {"fans": 936, "time": "2024-08-20 06:18:37", "rate1": 0, "rate7": -2}, {"fans": 935, "time": "2024-08-20 18:18:35", "rate1": -1, "rate7": -3}, {"fans": 935, "time": "2024-08-21 06:18:39", "rate1": -1, "rate7": -3}, {"fans": 935, "time": "2024-08-21 18:18:38", "rate1": 0, "rate7": -3}, {"fans": 935, "time": "2024-08-22 06:18:53", "rate1": 0, "rate7": -3}, {"fans": 935, "time": "2024-08-22 18:18:47", "rate1": 0, "rate7": -2}, {"fans": 935, "time": "2024-08-23 06:18:34", "rate1": 0, "rate7": -1}, {"fans": 935, "time": "2024-08-23 18:18:33", "rate1": 0, "rate7": -1}, {"fans": 935, "time": "2024-08-24 06:18:35", "rate1": 0, "rate7": -1}, {"fans": 935, "time": "2024-08-24 18:18:38", "rate1": 0, "rate7": -1}, {"fans": 935, "time": "2024-08-25 06:18:44", "rate1": 0, "rate7": -1}, {"fans": 935, "time": "2024-08-25 18:18:51", "rate1": 0, "rate7": -1}, {"fans": 935, "time": "2024-08-26 06:18:19", "rate1": 0, "rate7": -1}, {"fans": 935, "time": "2024-08-26 18:18:24", "rate1": 0, "rate7": -1}, {"fans": 935, "time": "2024-08-27 06:18:38", "rate1": 0, "rate7": -1}, {"fans": 935, "time": "2024-08-27 18:18:49", "rate1": 0, "rate7": 0}, {"fans": 935, "time": "2024-08-28 06:19:00", "rate1": 0, "rate7": 0}, {"fans": 935, "time": "2024-08-28 18:18:29", "rate1": 0, "rate7": 0}, {"fans": 935, "time": "2024-08-29 06:18:45", "rate1": 0, "rate7": 0}, {"fans": 935, "time": "2024-08-29 18:18:59", "rate1": 0, "rate7": 0}, {"fans": 935, "time": "2024-08-30 06:18:33", "rate1": 0, "rate7": 0}, {"fans": 935, "time": "2024-08-30 18:18:49", "rate1": 0, "rate7": 0}, {"fans": 935, "time": "2024-08-31 06:19:03", "rate1": 0, "rate7": 0}, {"fans": 935, "time": "2024-08-31 18:18:35", "rate1": 0, "rate7": 0}, {"fans": 935, "time": "2024-09-01 06:18:50", "rate1": 0, "rate7": 0}, {"fans": 935, "time": "2024-09-01 18:18:57", "rate1": 0, "rate7": 0}, {"fans": 935, "time": "2024-09-02 06:18:30", "rate1": 0, "rate7": 0}, {"fans": 935, "time": "2024-09-02 18:18:38", "rate1": 0, "rate7": 0}, {"fans": 935, "time": "2024-09-03 06:18:57", "rate1": 0, "rate7": 0}, {"fans": 935, "time": "2024-09-03 18:18:34", "rate1": 0, "rate7": 0}, {"fans": 935, "time": "2024-09-04 06:18:49", "rate1": 0, "rate7": 0}, {"fans": 935, "time": "2024-09-04 18:18:24", "rate1": 0, "rate7": 0}, {"fans": 935, "time": "2024-09-05 06:18:42", "rate1": 0, "rate7": 0}, {"fans": 935, "time": "2024-09-05 18:19:04", "rate1": 0, "rate7": 0}, {"fans": 935, "time": "2024-09-06 06:18:47", "rate1": 0, "rate7": 0}, {"fans": 934, "time": "2024-09-06 18:18:28", "rate1": -1, "rate7": -1}]