[{"fans": 1852, "time": "2023-10-09 18:47:35"}, {"fans": 2080, "time": "2023-10-10 06:47:20"}, {"fans": 2221, "time": "2023-10-10 18:47:32", "rate1": 369}, {"fans": 2369, "time": "2023-10-11 06:47:57", "rate1": 289}, {"fans": 2645, "time": "2023-10-11 18:47:59", "rate1": 424}, {"fans": 3348, "time": "2023-10-12 06:48:05", "rate1": 979}, {"fans": 3740, "time": "2023-10-12 18:48:11", "rate1": 1095}, {"fans": 4112, "time": "2023-10-13 06:48:18", "rate1": 764}, {"fans": 4392, "time": "2023-10-13 18:48:28", "rate1": 652}, {"fans": 4607, "time": "2023-10-14 06:48:34", "rate1": 495}, {"fans": 4762, "time": "2023-10-14 18:48:48", "rate1": 370}, {"fans": 4860, "time": "2023-10-15 06:48:29", "rate1": 253}, {"fans": 4934, "time": "2023-10-15 18:48:53", "rate1": 172}, {"fans": 5067, "time": "2023-10-16 06:48:40", "rate1": 207}, {"fans": 5175, "time": "2023-10-16 18:48:28", "rate1": 241, "rate7": 3323}, {"fans": 5434, "time": "2023-10-17 06:48:54", "rate1": 367, "rate7": 3354}, {"fans": 5566, "time": "2023-10-17 18:48:47", "rate1": 391, "rate7": 3345}, {"fans": 5659, "time": "2023-10-18 06:48:39", "rate1": 225, "rate7": 3290}, {"fans": 5709, "time": "2023-10-18 18:48:34", "rate1": 143, "rate7": 3064}, {"fans": 5755, "time": "2023-10-19 06:49:26", "rate1": 96, "rate7": 2407}, {"fans": 5788, "time": "2023-10-19 18:49:01", "rate1": 79, "rate7": 2048}, {"fans": 5836, "time": "2023-10-20 06:49:12", "rate1": 81, "rate7": 1724}, {"fans": 5856, "time": "2023-10-20 18:49:35", "rate1": 68, "rate7": 1464}, {"fans": 5898, "time": "2023-10-21 06:49:17", "rate1": 62, "rate7": 1291}, {"fans": 5927, "time": "2023-10-21 18:49:11", "rate1": 71, "rate7": 1165}, {"fans": 5973, "time": "2023-10-22 06:49:43", "rate1": 75, "rate7": 1113}, {"fans": 5997, "time": "2023-10-22 18:49:44", "rate1": 70, "rate7": 1063}, {"fans": 6028, "time": "2023-10-23 06:49:47", "rate1": 55, "rate7": 961}, {"fans": 6054, "time": "2023-10-23 18:49:52", "rate1": 57, "rate7": 879}, {"fans": 6109, "time": "2023-10-24 06:50:05", "rate1": 81, "rate7": 675}, {"fans": 6163, "time": "2023-10-24 18:49:50", "rate1": 109, "rate7": 597}, {"fans": 6224, "time": "2023-10-25 06:50:44", "rate1": 115, "rate7": 565}, {"fans": 6271, "time": "2023-10-25 18:50:20", "rate1": 108, "rate7": 562}, {"fans": 6312, "time": "2023-10-26 06:50:39", "rate1": 88, "rate7": 557}, {"fans": 6332, "time": "2023-10-26 18:50:29", "rate1": 61, "rate7": 544}, {"fans": 6353, "time": "2023-10-27 06:50:58", "rate1": 41, "rate7": 517}, {"fans": 6362, "time": "2023-10-27 18:51:01", "rate1": 30, "rate7": 506}, {"fans": 6385, "time": "2023-10-28 06:51:10", "rate1": 32, "rate7": 487}, {"fans": 6402, "time": "2023-10-28 18:50:43", "rate1": 40, "rate7": 475}, {"fans": 6414, "time": "2023-10-29 06:51:33", "rate1": 29, "rate7": 441}, {"fans": 6434, "time": "2023-10-29 18:51:58", "rate1": 32, "rate7": 437}, {"fans": 6452, "time": "2023-10-30 06:51:59", "rate1": 38, "rate7": 424}, {"fans": 6467, "time": "2023-10-30 18:52:02", "rate1": 33, "rate7": 413}, {"fans": 6480, "time": "2023-10-31 06:52:07", "rate1": 28, "rate7": 371}, {"fans": 6483, "time": "2023-10-31 18:52:18", "rate1": 16, "rate7": 320}, {"fans": 6490, "time": "2023-11-01 06:52:28", "rate1": 10, "rate7": 266}, {"fans": 6508, "time": "2023-11-01 18:52:44", "rate1": 25, "rate7": 237}, {"fans": 6534, "time": "2023-11-02 06:52:14", "rate1": 44, "rate7": 222}, {"fans": 6539, "time": "2023-11-02 18:52:32", "rate1": 31, "rate7": 207}, {"fans": 6546, "time": "2023-11-03 06:52:02", "rate1": 12, "rate7": 193}, {"fans": 6558, "time": "2023-11-03 18:52:18", "rate1": 19, "rate7": 196}, {"fans": 6566, "time": "2023-11-04 06:52:38", "rate1": 20, "rate7": 181}, {"fans": 6571, "time": "2023-11-04 18:52:22", "rate1": 13, "rate7": 169}, {"fans": 6572, "time": "2023-11-05 06:52:43", "rate1": 6, "rate7": 158}, {"fans": 6578, "time": "2023-11-05 18:52:27", "rate1": 7, "rate7": 144}, {"fans": 6593, "time": "2023-11-06 06:52:58", "rate1": 21, "rate7": 141}, {"fans": 6602, "time": "2023-11-06 18:53:11", "rate1": 24, "rate7": 135}, {"fans": 6614, "time": "2023-11-07 06:52:43", "rate1": 21, "rate7": 134}, {"fans": 6618, "time": "2023-11-07 18:53:02", "rate1": 16, "rate7": 135}, {"fans": 6628, "time": "2023-11-08 06:53:33", "rate1": 14, "rate7": 138}, {"fans": 6627, "time": "2023-11-08 18:53:21", "rate1": 9, "rate7": 119}, {"fans": 6629, "time": "2023-11-09 06:53:08", "rate1": 1, "rate7": 95}, {"fans": 6636, "time": "2023-11-09 18:53:40", "rate1": 9, "rate7": 97}, {"fans": 6642, "time": "2023-11-10 06:53:26", "rate1": 13, "rate7": 96}, {"fans": 6635, "time": "2023-11-10 18:53:23", "rate1": -1, "rate7": 77}, {"fans": 6637, "time": "2023-11-11 06:53:09", "rate1": -5, "rate7": 71}, {"fans": 6639, "time": "2023-11-11 18:53:46", "rate1": 4, "rate7": 68}, {"fans": 6637, "time": "2023-11-12 06:53:41", "rate1": 0, "rate7": 65}, {"fans": 6640, "time": "2023-11-12 18:53:35", "rate1": 1, "rate7": 62}, {"fans": 6640, "time": "2023-11-13 06:53:28", "rate1": 3, "rate7": 47}, {"fans": 6643, "time": "2023-11-13 18:53:28", "rate1": 3, "rate7": 41}, {"fans": 6646, "time": "2023-11-14 06:53:25", "rate1": 6, "rate7": 32}, {"fans": 6646, "time": "2023-11-14 18:53:30", "rate1": 3, "rate7": 28}, {"fans": 6651, "time": "2023-11-15 06:54:09", "rate1": 5, "rate7": 23}, {"fans": 6645, "time": "2023-11-15 18:54:35", "rate1": -1, "rate7": 18}, {"fans": 6644, "time": "2023-11-16 06:54:16", "rate1": -7, "rate7": 15}, {"fans": 6645, "time": "2023-11-16 18:53:57", "rate1": 0, "rate7": 9}, {"fans": 6649, "time": "2023-11-17 06:53:48", "rate1": 5, "rate7": 7}, {"fans": 6649, "time": "2023-11-17 18:54:10", "rate1": 4, "rate7": 14}, {"fans": 6646, "time": "2023-11-18 06:54:00", "rate1": -3, "rate7": 9}, {"fans": 6647, "time": "2023-11-18 18:55:52", "rate1": -2, "rate7": 8}, {"fans": 6648, "time": "2023-11-19 06:53:41", "rate1": 2, "rate7": 11}, {"fans": 6643, "time": "2023-11-19 18:54:13", "rate1": -4, "rate7": 3}, {"fans": 6644, "time": "2023-11-20 06:54:06", "rate1": -4, "rate7": 4}, {"fans": 6645, "time": "2023-11-20 18:54:48", "rate1": 2, "rate7": 2}, {"fans": 6649, "time": "2023-11-21 06:54:53", "rate1": 5, "rate7": 3}, {"fans": 6652, "time": "2023-11-21 18:54:20", "rate1": 7, "rate7": 6}, {"fans": 6652, "time": "2023-11-22 06:54:27", "rate1": 3, "rate7": 1}, {"fans": 6650, "time": "2023-11-22 18:54:58", "rate1": -2, "rate7": 5}, {"fans": -1, "time": "2023-11-23 06:54:39", "rate1": -6653, "rate7": -6645}, {"fans": -1, "time": "2023-11-23 18:54:26", "rate1": -6651, "rate7": -6646}, {"fans": -1, "time": "2023-11-24 06:55:02", "rate1": 0, "rate7": -6650}, {"fans": 6667, "time": "2023-11-24 18:55:49", "rate1": 6668, "rate7": 18}, {"fans": 6667, "time": "2023-11-25 08:03:33", "rate1": 6668, "rate7": 21}, {"fans": 6668, "time": "2023-11-25 20:05:17", "rate1": 1, "rate7": 21}, {"fans": 6667, "time": "2023-11-26 08:06:14", "rate1": 0, "rate7": 19}, {"fans": 6674, "time": "2023-11-26 20:08:37", "rate1": 6, "rate7": 31}, {"fans": 6674, "time": "2023-11-27 08:06:42", "rate1": 7, "rate7": 30}, {"fans": 6671, "time": "2023-11-27 20:44:01", "rate1": -3, "rate7": 26}, {"fans": 6672, "time": "2023-11-28 09:21:22", "rate1": -2, "rate7": 23}, {"fans": 6672, "time": "2023-11-28 23:18:10", "rate1": 1, "rate7": 20}, {"fans": 6673, "time": "2023-11-29 08:36:29", "rate1": 1, "rate7": 21}, {"fans": 6673, "time": "2023-11-29 21:42:31", "rate1": 1, "rate7": 23}, {"fans": 6668, "time": "2023-11-30 09:09:03", "rate1": -5, "rate7": 6669}, {"fans": 6668, "time": "2023-11-30 21:14:09", "rate1": -5, "rate7": 6669}, {"fans": 6669, "time": "2023-12-01 08:21:51", "rate1": 1, "rate7": 6670}, {"fans": 6668, "time": "2023-12-01 20:35:11", "rate1": 0, "rate7": 1}, {"fans": 6665, "time": "2023-12-02 08:16:27", "rate1": -4, "rate7": -2}, {"fans": 6668, "time": "2023-12-02 21:14:43", "rate1": 0, "rate7": 0}, {"fans": 6669, "time": "2023-12-03 08:31:34", "rate1": 4, "rate7": 2}, {"fans": 6690, "time": "2023-12-03 20:40:34", "rate1": 22, "rate7": 16}, {"fans": 6695, "time": "2023-12-04 08:24:26", "rate1": 26, "rate7": 21}, {"fans": 6699, "time": "2023-12-04 21:15:55", "rate1": 9, "rate7": 28}, {"fans": 6702, "time": "2023-12-05 08:29:19", "rate1": 7, "rate7": 30}, {"fans": 6708, "time": "2023-12-05 20:17:20", "rate1": 9, "rate7": 36}, {"fans": 6714, "time": "2023-12-06 08:07:13", "rate1": 12, "rate7": 41}, {"fans": 6719, "time": "2023-12-06 20:37:49", "rate1": 11, "rate7": 46}, {"fans": 6717, "time": "2023-12-07 08:23:13", "rate1": 3, "rate7": 49}, {"fans": 6717, "time": "2023-12-07 20:47:52", "rate1": -2, "rate7": 49}, {"fans": 6717, "time": "2023-12-08 08:26:24", "rate1": 0, "rate7": 48}, {"fans": 6718, "time": "2023-12-08 19:42:41", "rate1": 1, "rate7": 50}, {"fans": 6724, "time": "2023-12-09 08:32:11", "rate1": 7, "rate7": 59}, {"fans": 6728, "time": "2023-12-09 19:55:07", "rate1": 10, "rate7": 60}, {"fans": 6732, "time": "2023-12-10 09:33:44", "rate1": 8, "rate7": 63}, {"fans": 6735, "time": "2023-12-10 21:01:00", "rate1": 7, "rate7": 45}, {"fans": 6741, "time": "2023-12-11 08:42:43", "rate1": 9, "rate7": 46}, {"fans": 6739, "time": "2023-12-11 21:01:32", "rate1": 4, "rate7": 40}, {"fans": 6742, "time": "2023-12-12 08:57:42", "rate1": 1, "rate7": 40}, {"fans": 6750, "time": "2023-12-12 20:23:48", "rate1": 11, "rate7": 42}, {"fans": 6751, "time": "2023-12-13 08:12:38", "rate1": 9, "rate7": 37}, {"fans": 6760, "time": "2023-12-13 21:09:54", "rate1": 10, "rate7": 41}, {"fans": 6763, "time": "2023-12-14 08:22:14", "rate1": 12, "rate7": 46}, {"fans": 6766, "time": "2023-12-14 22:25:24", "rate1": 6, "rate7": 49}, {"fans": 6769, "time": "2023-12-15 08:40:56", "rate1": 6, "rate7": 52}, {"fans": 6769, "time": "2023-12-15 21:50:16", "rate1": 3, "rate7": 51}, {"fans": 6768, "time": "2023-12-16 09:22:15", "rate1": -1, "rate7": 44}, {"fans": 6769, "time": "2023-12-16 23:39:37", "rate1": 0, "rate7": 41}, {"fans": 6771, "time": "2023-12-17 08:45:54", "rate1": 3, "rate7": 39}, {"fans": 6775, "time": "2023-12-17 21:25:05", "rate1": 6, "rate7": 40}, {"fans": 6776, "time": "2023-12-18 08:35:56", "rate1": 5, "rate7": 35}, {"fans": 6774, "time": "2023-12-18 21:28:24", "rate1": -1, "rate7": 35}, {"fans": 6774, "time": "2023-12-19 08:41:48", "rate1": -2, "rate7": 32}, {"fans": 6774, "time": "2023-12-19 22:21:22", "rate1": 0, "rate7": 24}, {"fans": 6786, "time": "2023-12-20 09:11:47", "rate1": 12, "rate7": 35}, {"fans": 6919, "time": "2023-12-20 20:40:13", "rate1": 145, "rate7": 159}, {"fans": 6976, "time": "2023-12-21 09:08:35", "rate1": 190, "rate7": 213}, {"fans": 6976, "time": "2023-12-21 21:23:04", "rate1": 57, "rate7": 210}, {"fans": 7054, "time": "2023-12-22 08:35:27", "rate1": 78, "rate7": 285}, {"fans": 7060, "time": "2023-12-22 20:48:49", "rate1": 84, "rate7": 291}, {"fans": 7063, "time": "2023-12-23 09:10:39", "rate1": 9, "rate7": 295}, {"fans": 7066, "time": "2023-12-23 20:52:06", "rate1": 6, "rate7": 297}, {"fans": 7066, "time": "2023-12-24 08:43:22", "rate1": 3, "rate7": 295}, {"fans": 7072, "time": "2023-12-24 21:59:15", "rate1": 6, "rate7": 297}, {"fans": 7072, "time": "2023-12-25 09:02:22", "rate1": 6, "rate7": 296}, {"fans": 7068, "time": "2023-12-25 20:54:39", "rate1": -4, "rate7": 294}, {"fans": 7073, "time": "2023-12-26 08:39:30", "rate1": 1, "rate7": 299}, {"fans": 7078, "time": "2023-12-26 22:00:42", "rate1": 10, "rate7": 304}, {"fans": 7083, "time": "2023-12-27 08:15:56", "rate1": 10, "rate7": 297}, {"fans": 7083, "time": "2023-12-27 21:45:37", "rate1": -1, "rate7": -1}, {"fans": 7089, "time": "2023-12-28 08:33:27", "rate1": 6, "rate7": 113}, {"fans": 7098, "time": "2023-12-28 20:45:35", "rate1": 15, "rate7": 122}, {"fans": 7107, "time": "2023-12-29 08:25:10", "rate1": 18, "rate7": 53}, {"fans": 7116, "time": "2023-12-29 20:27:10", "rate1": 18, "rate7": 56}, {"fans": 7116, "time": "2023-12-30 08:00:20", "rate1": 9, "rate7": 53}, {"fans": 7116, "time": "2023-12-30 21:59:18", "rate1": -1, "rate7": -1}, {"fans": 7133, "time": "2023-12-31 08:20:28", "rate1": 17, "rate7": 67}, {"fans": 7137, "time": "2023-12-31 20:15:08", "rate1": 21, "rate7": 65}, {"fans": 7144, "time": "2024-01-01 08:32:38", "rate1": 11, "rate7": 72}, {"fans": 7160, "time": "2024-01-01 20:28:44", "rate1": 23, "rate7": 92}, {"fans": 7161, "time": "2024-01-02 08:40:15", "rate1": 17, "rate7": 88}, {"fans": 7161, "time": "2024-01-02 21:45:18", "rate1": 1, "rate7": 83}, {"fans": 7162, "time": "2024-01-03 10:51:08", "rate1": 1, "rate7": 79}, {"fans": 7163, "time": "2024-01-03 23:31:54", "rate1": 2, "rate7": 80}, {"fans": 7162, "time": "2024-01-04 09:48:24", "rate1": 0, "rate7": 73}, {"fans": 7166, "time": "2024-01-05 01:51:20", "rate1": 3, "rate7": 68}, {"fans": 7166, "time": "2024-01-05 13:20:52", "rate1": -1, "rate7": -1}, {"fans": 7168, "time": "2024-01-06 06:47:06", "rate1": 2, "rate7": 52}, {"fans": 7170, "time": "2024-01-06 18:47:46", "rate1": 4, "rate7": 54}, {"fans": 7168, "time": "2024-01-07 06:47:42", "rate1": 0, "rate7": 52}, {"fans": 7168, "time": "2024-01-07 18:47:41", "rate1": -2, "rate7": 35}, {"fans": 7167, "time": "2024-01-08 06:47:37", "rate1": -1, "rate7": 30}, {"fans": 7170, "time": "2024-01-08 18:47:35", "rate1": 2, "rate7": 26}, {"fans": 7166, "time": "2024-01-09 06:47:34", "rate1": -1, "rate7": 6}, {"fans": 7166, "time": "2024-01-09 18:47:40", "rate1": -4, "rate7": 5}, {"fans": 7165, "time": "2024-01-10 06:47:48", "rate1": -1, "rate7": 4}, {"fans": 7166, "time": "2024-01-10 18:48:06", "rate1": 0, "rate7": 4}, {"fans": 7167, "time": "2024-01-11 06:47:45", "rate1": 2, "rate7": 4}, {"fans": 7169, "time": "2024-01-11 18:48:15", "rate1": 3, "rate7": 7}, {"fans": 7173, "time": "2024-01-12 06:47:59", "rate1": 6, "rate7": 7}, {"fans": 7175, "time": "2024-01-12 18:47:47", "rate1": 6, "rate7": 9}, {"fans": 7175, "time": "2024-01-13 06:47:43", "rate1": 2, "rate7": 7}, {"fans": 7173, "time": "2024-01-13 18:48:29", "rate1": -2, "rate7": 3}, {"fans": 7174, "time": "2024-01-14 06:47:54", "rate1": -1, "rate7": 6}, {"fans": 7169, "time": "2024-01-14 18:48:08", "rate1": -4, "rate7": 1}, {"fans": 7169, "time": "2024-01-15 06:48:21", "rate1": -5, "rate7": 2}, {"fans": 7173, "time": "2024-01-15 18:48:36", "rate1": 4, "rate7": 3}, {"fans": 7176, "time": "2024-01-16 06:48:08", "rate1": 7, "rate7": 10}, {"fans": 7179, "time": "2024-01-16 18:48:30", "rate1": 6, "rate7": 13}, {"fans": 7180, "time": "2024-01-17 06:48:07", "rate1": 4, "rate7": 15}, {"fans": 7179, "time": "2024-01-17 18:49:04", "rate1": 0, "rate7": 13}, {"fans": 7182, "time": "2024-01-18 06:48:20", "rate1": 2, "rate7": 15}, {"fans": 7181, "time": "2024-01-18 18:49:33", "rate1": 2, "rate7": 12}, {"fans": 7180, "time": "2024-01-19 06:49:12", "rate1": -2, "rate7": 7}, {"fans": 7179, "time": "2024-01-19 18:48:58", "rate1": -2, "rate7": 4}, {"fans": 7180, "time": "2024-01-20 06:49:17", "rate1": 0, "rate7": 5}, {"fans": 7183, "time": "2024-01-20 18:49:06", "rate1": 4, "rate7": 10}, {"fans": 7179, "time": "2024-01-21 06:48:56", "rate1": -1, "rate7": 5}, {"fans": 7179, "time": "2024-01-21 18:49:37", "rate1": -4, "rate7": 10}, {"fans": 7181, "time": "2024-01-22 06:49:36", "rate1": 2, "rate7": 12}, {"fans": 7182, "time": "2024-01-22 18:49:43", "rate1": 3, "rate7": 9}, {"fans": 7184, "time": "2024-01-23 06:49:42", "rate1": 3, "rate7": 8}, {"fans": 7181, "time": "2024-01-23 18:49:58", "rate1": -1, "rate7": 2}, {"fans": 7181, "time": "2024-01-24 06:49:25", "rate1": -3, "rate7": 1}, {"fans": 7178, "time": "2024-01-24 18:49:42", "rate1": -3, "rate7": -1}, {"fans": 7173, "time": "2024-01-25 06:49:48", "rate1": -8, "rate7": -9}, {"fans": 7171, "time": "2024-01-25 18:49:35", "rate1": -7, "rate7": -10}, {"fans": 7169, "time": "2024-01-26 06:49:58", "rate1": -4, "rate7": -11}, {"fans": 7167, "time": "2024-01-26 18:49:48", "rate1": -4, "rate7": -12}, {"fans": 7165, "time": "2024-01-27 06:49:34", "rate1": -4, "rate7": -15}, {"fans": 7164, "time": "2024-01-27 18:50:07", "rate1": -3, "rate7": -19}, {"fans": 7163, "time": "2024-01-28 06:50:06", "rate1": -2, "rate7": -16}, {"fans": 7161, "time": "2024-01-28 18:50:23", "rate1": -3, "rate7": -18}, {"fans": 7160, "time": "2024-01-29 06:50:46", "rate1": -3, "rate7": -21}, {"fans": 7158, "time": "2024-01-29 18:50:38", "rate1": -3, "rate7": -24}, {"fans": 7160, "time": "2024-01-30 06:50:21", "rate1": 0, "rate7": -24}, {"fans": 7156, "time": "2024-01-30 18:50:49", "rate1": -2, "rate7": -25}, {"fans": 7156, "time": "2024-01-31 06:50:36", "rate1": -4, "rate7": -25}, {"fans": 7156, "time": "2024-01-31 18:50:37", "rate1": 0, "rate7": -22}, {"fans": 7155, "time": "2024-02-01 06:50:41", "rate1": -1, "rate7": -18}, {"fans": 7154, "time": "2024-02-01 18:50:51", "rate1": -2, "rate7": -17}, {"fans": 7152, "time": "2024-02-02 06:51:00", "rate1": -3, "rate7": -17}, {"fans": 7153, "time": "2024-02-02 18:51:15", "rate1": -1, "rate7": -14}, {"fans": 7151, "time": "2024-02-03 06:50:46", "rate1": -1, "rate7": -14}, {"fans": 7150, "time": "2024-02-03 18:51:14", "rate1": -3, "rate7": -14}, {"fans": 7149, "time": "2024-02-04 06:50:59", "rate1": -2, "rate7": -14}, {"fans": 7148, "time": "2024-02-04 18:51:31", "rate1": -2, "rate7": -13}, {"fans": 7148, "time": "2024-02-05 06:51:24", "rate1": -1, "rate7": -12}, {"fans": 7146, "time": "2024-02-05 18:51:22", "rate1": -2, "rate7": -12}, {"fans": 7147, "time": "2024-02-06 06:51:33", "rate1": -1, "rate7": -13}, {"fans": 7150, "time": "2024-02-06 18:51:50", "rate1": 4, "rate7": -6}, {"fans": 7152, "time": "2024-02-07 06:51:24", "rate1": 5, "rate7": -4}, {"fans": 7150, "time": "2024-02-07 18:51:41", "rate1": 0, "rate7": -6}, {"fans": 7152, "time": "2024-02-08 06:51:18", "rate1": 0, "rate7": -3}, {"fans": 7152, "time": "2024-02-08 18:51:39", "rate1": 2, "rate7": -2}, {"fans": 7154, "time": "2024-02-09 06:52:00", "rate1": 2, "rate7": 2}, {"fans": 7154, "time": "2024-02-09 18:51:43", "rate1": 2, "rate7": 1}, {"fans": 7159, "time": "2024-02-10 06:51:29", "rate1": 5, "rate7": 8}, {"fans": 7160, "time": "2024-02-10 18:51:57", "rate1": 6, "rate7": 10}, {"fans": 7159, "time": "2024-02-11 06:51:43", "rate1": 0, "rate7": 10}, {"fans": 7155, "time": "2024-02-11 18:51:31", "rate1": -5, "rate7": 7}, {"fans": 7155, "time": "2024-02-12 06:51:56", "rate1": -4, "rate7": 7}, {"fans": 7152, "time": "2024-02-12 18:51:44", "rate1": -3, "rate7": 6}, {"fans": 7151, "time": "2024-02-13 06:51:34", "rate1": -4, "rate7": 4}, {"fans": 7152, "time": "2024-02-13 18:52:11", "rate1": 0, "rate7": 2}, {"fans": 7150, "time": "2024-02-14 06:52:21", "rate1": -1, "rate7": -2}, {"fans": 7152, "time": "2024-02-14 18:51:58", "rate1": 0, "rate7": 2}, {"fans": 7149, "time": "2024-02-15 06:52:17", "rate1": -1, "rate7": -3}, {"fans": 7148, "time": "2024-02-15 18:52:13", "rate1": -4, "rate7": -4}, {"fans": 7149, "time": "2024-02-16 06:52:43", "rate1": 0, "rate7": -5}, {"fans": 7150, "time": "2024-02-16 18:52:38", "rate1": 2, "rate7": -4}, {"fans": 7147, "time": "2024-02-17 06:52:39", "rate1": -2, "rate7": -12}, {"fans": 7147, "time": "2024-02-17 18:52:47", "rate1": -3, "rate7": -13}, {"fans": 7148, "time": "2024-02-18 06:52:54", "rate1": 1, "rate7": -11}, {"fans": 7149, "time": "2024-02-18 18:53:07", "rate1": 2, "rate7": -6}, {"fans": 7147, "time": "2024-02-19 06:52:33", "rate1": -1, "rate7": -8}, {"fans": 7146, "time": "2024-02-19 18:52:46", "rate1": -3, "rate7": -6}, {"fans": 7147, "time": "2024-02-20 06:52:56", "rate1": 0, "rate7": -4}, {"fans": 7148, "time": "2024-02-20 18:53:22", "rate1": 2, "rate7": -4}, {"fans": 7146, "time": "2024-02-21 06:52:57", "rate1": -1, "rate7": -4}, {"fans": 7147, "time": "2024-02-21 18:52:40", "rate1": -1, "rate7": -5}, {"fans": 7148, "time": "2024-02-22 06:52:55", "rate1": 2, "rate7": -1}, {"fans": 7147, "time": "2024-02-22 18:53:20", "rate1": 0, "rate7": -1}, {"fans": 7146, "time": "2024-02-23 06:53:07", "rate1": -2, "rate7": -3}, {"fans": 7146, "time": "2024-02-23 18:53:03", "rate1": -1, "rate7": -4}, {"fans": 7146, "time": "2024-02-24 06:52:54", "rate1": 0, "rate7": -1}, {"fans": 7146, "time": "2024-02-24 18:53:31", "rate1": 0, "rate7": -1}, {"fans": 7147, "time": "2024-02-25 06:53:26", "rate1": 1, "rate7": -1}, {"fans": 7145, "time": "2024-02-25 18:53:26", "rate1": -1, "rate7": -4}, {"fans": 7145, "time": "2024-02-26 06:53:21", "rate1": -2, "rate7": -2}, {"fans": 7144, "time": "2024-02-26 18:53:23", "rate1": -1, "rate7": -2}, {"fans": 7145, "time": "2024-02-27 06:53:19", "rate1": 0, "rate7": -2}, {"fans": 7145, "time": "2024-02-27 18:53:19", "rate1": 1, "rate7": -3}, {"fans": 7145, "time": "2024-02-28 06:53:18", "rate1": 0, "rate7": -1}, {"fans": 7146, "time": "2024-02-28 18:53:26", "rate1": 1, "rate7": -1}, {"fans": 7145, "time": "2024-02-29 06:53:30", "rate1": 0, "rate7": -3}, {"fans": 7143, "time": "2024-02-29 18:53:43", "rate1": -3, "rate7": -4}, {"fans": 7148, "time": "2024-03-01 06:53:18", "rate1": 3, "rate7": 2}, {"fans": 7156, "time": "2024-03-01 18:53:43", "rate1": 13, "rate7": 10}, {"fans": 7158, "time": "2024-03-02 06:53:19", "rate1": 10, "rate7": 12}, {"fans": 7162, "time": "2024-03-02 18:53:41", "rate1": 6, "rate7": 16}, {"fans": 7161, "time": "2024-03-03 06:53:21", "rate1": 3, "rate7": 14}, {"fans": 7158, "time": "2024-03-03 18:53:46", "rate1": -4, "rate7": 13}, {"fans": 7156, "time": "2024-03-04 06:53:25", "rate1": -5, "rate7": 11}, {"fans": 7157, "time": "2024-03-04 18:53:48", "rate1": -1, "rate7": 13}, {"fans": 7157, "time": "2024-03-05 06:53:32", "rate1": 1, "rate7": 12}, {"fans": 7157, "time": "2024-03-05 18:54:00", "rate1": 0, "rate7": 12}, {"fans": 7158, "time": "2024-03-06 06:54:30", "rate1": 1, "rate7": 13}, {"fans": 7158, "time": "2024-03-06 18:53:59", "rate1": 1, "rate7": 12}, {"fans": 7158, "time": "2024-03-07 06:54:15", "rate1": 0, "rate7": 13}, {"fans": 7158, "time": "2024-03-07 18:54:28", "rate1": 0, "rate7": 15}, {"fans": 7157, "time": "2024-03-08 06:53:59", "rate1": -1, "rate7": 9}, {"fans": 7157, "time": "2024-03-08 18:54:12", "rate1": -1, "rate7": 1}, {"fans": 7157, "time": "2024-03-09 06:54:22", "rate1": 0, "rate7": -1}, {"fans": 7155, "time": "2024-03-09 18:53:55", "rate1": -2, "rate7": -7}, {"fans": 7154, "time": "2024-03-10 06:54:07", "rate1": -3, "rate7": -7}, {"fans": 7156, "time": "2024-03-10 18:54:22", "rate1": 1, "rate7": -2}, {"fans": 7159, "time": "2024-03-11 06:53:48", "rate1": 5, "rate7": 3}, {"fans": 7159, "time": "2024-03-11 18:54:01", "rate1": 3, "rate7": 2}, {"fans": 7158, "time": "2024-03-12 06:54:10", "rate1": -1, "rate7": 1}, {"fans": 7151, "time": "2024-03-12 18:54:22", "rate1": -8, "rate7": -6}, {"fans": 7153, "time": "2024-03-13 06:53:56", "rate1": -5, "rate7": -5}, {"fans": 7152, "time": "2024-03-13 18:54:14", "rate1": 1, "rate7": -6}, {"fans": 7152, "time": "2024-03-14 06:54:27", "rate1": -1, "rate7": -6}, {"fans": 7151, "time": "2024-03-14 18:54:07", "rate1": -1, "rate7": -7}, {"fans": 7153, "time": "2024-03-15 06:54:25", "rate1": 1, "rate7": -4}, {"fans": 7153, "time": "2024-03-15 18:54:09", "rate1": 2, "rate7": -4}, {"fans": 7150, "time": "2024-03-16 06:54:31", "rate1": -3, "rate7": -7}, {"fans": 7151, "time": "2024-03-16 18:54:18", "rate1": -2, "rate7": -4}, {"fans": 7149, "time": "2024-03-17 06:54:00", "rate1": -1, "rate7": -5}, {"fans": 7149, "time": "2024-03-17 18:54:28", "rate1": -2, "rate7": -7}, {"fans": 7150, "time": "2024-03-18 06:54:09", "rate1": 1, "rate7": -9}, {"fans": 7150, "time": "2024-03-18 18:54:34", "rate1": 1, "rate7": -9}, {"fans": 7148, "time": "2024-03-19 06:54:17", "rate1": -2, "rate7": -10}, {"fans": 7148, "time": "2024-03-19 18:54:04", "rate1": -2, "rate7": -3}, {"fans": 7145, "time": "2024-03-20 06:54:26", "rate1": -3, "rate7": -8}, {"fans": 7146, "time": "2024-03-20 18:54:12", "rate1": -2, "rate7": -6}, {"fans": 7147, "time": "2024-03-21 06:54:32", "rate1": 2, "rate7": -5}, {"fans": 7145, "time": "2024-03-21 18:54:21", "rate1": -1, "rate7": -6}, {"fans": 7145, "time": "2024-03-22 06:54:08", "rate1": -2, "rate7": -8}, {"fans": 7144, "time": "2024-03-22 18:54:37", "rate1": -1, "rate7": -9}, {"fans": 7145, "time": "2024-03-23 06:54:27", "rate1": 0, "rate7": -5}, {"fans": 7147, "time": "2024-03-23 18:54:23", "rate1": 3, "rate7": -4}, {"fans": 7147, "time": "2024-03-24 06:54:15", "rate1": 2, "rate7": -2}, {"fans": 7148, "time": "2024-03-24 18:54:11", "rate1": 1, "rate7": -1}, {"fans": 7148, "time": "2024-03-25 06:54:39", "rate1": 1, "rate7": -2}, {"fans": 7147, "time": "2024-03-25 18:54:40", "rate1": -1, "rate7": -3}, {"fans": 7147, "time": "2024-03-26 06:54:33", "rate1": -1, "rate7": -1}, {"fans": 7149, "time": "2024-03-26 18:54:31", "rate1": 2, "rate7": 1}, {"fans": 7150, "time": "2024-03-27 06:54:23", "rate1": 3, "rate7": 5}, {"fans": 7152, "time": "2024-03-27 18:54:20", "rate1": 3, "rate7": 6}, {"fans": 7150, "time": "2024-03-28 06:54:22", "rate1": 0, "rate7": 3}, {"fans": 7149, "time": "2024-03-28 18:54:25", "rate1": -3, "rate7": 4}, {"fans": 7147, "time": "2024-03-29 06:54:27", "rate1": -3, "rate7": 2}, {"fans": 7145, "time": "2024-03-29 18:54:31", "rate1": -4, "rate7": 1}, {"fans": 7144, "time": "2024-03-30 06:54:31", "rate1": -3, "rate7": -1}, {"fans": 7142, "time": "2024-03-30 18:54:39", "rate1": -3, "rate7": -5}, {"fans": 7140, "time": "2024-03-31 06:54:40", "rate1": -4, "rate7": -7}, {"fans": 7140, "time": "2024-03-31 18:54:50", "rate1": -2, "rate7": -8}, {"fans": 7141, "time": "2024-04-01 06:54:21", "rate1": 1, "rate7": -7}, {"fans": 7140, "time": "2024-04-01 18:54:33", "rate1": 0, "rate7": -7}, {"fans": 7140, "time": "2024-04-02 06:54:37", "rate1": -1, "rate7": -7}, {"fans": 7133, "time": "2024-04-02 18:54:45", "rate1": -7, "rate7": -16}, {"fans": 7135, "time": "2024-04-03 06:54:50", "rate1": -5, "rate7": -15}, {"fans": 7135, "time": "2024-04-03 18:54:25", "rate1": 2, "rate7": -17}, {"fans": 7136, "time": "2024-04-04 06:54:36", "rate1": 1, "rate7": -14}, {"fans": 7134, "time": "2024-04-04 18:54:54", "rate1": -1, "rate7": -15}, {"fans": 7136, "time": "2024-04-05 06:54:26", "rate1": 0, "rate7": -11}, {"fans": 7135, "time": "2024-04-05 18:54:45", "rate1": 1, "rate7": -10}, {"fans": 7136, "time": "2024-04-06 06:54:17", "rate1": 0, "rate7": -8}, {"fans": 7135, "time": "2024-04-06 18:54:39", "rate1": 0, "rate7": -7}, {"fans": 7137, "time": "2024-04-07 06:54:55", "rate1": 1, "rate7": -3}, {"fans": 7135, "time": "2024-04-07 18:54:36", "rate1": 0, "rate7": -5}, {"fans": 7138, "time": "2024-04-08 06:54:52", "rate1": 1, "rate7": -3}, {"fans": 7136, "time": "2024-04-08 18:54:32", "rate1": 1, "rate7": -4}, {"fans": 7138, "time": "2024-04-09 06:54:47", "rate1": 0, "rate7": -2}, {"fans": 7139, "time": "2024-04-09 18:54:27", "rate1": 3, "rate7": 6}, {"fans": 7136, "time": "2024-04-10 06:54:41", "rate1": -2, "rate7": 1}, {"fans": 7137, "time": "2024-04-10 18:54:20", "rate1": -2, "rate7": 2}, {"fans": 7134, "time": "2024-04-11 06:54:34", "rate1": -2, "rate7": -2}, {"fans": 7133, "time": "2024-04-11 18:54:51", "rate1": -4, "rate7": -1}, {"fans": 7135, "time": "2024-04-12 06:54:27", "rate1": 1, "rate7": -1}, {"fans": 7133, "time": "2024-04-12 18:54:46", "rate1": 0, "rate7": -2}, {"fans": 7132, "time": "2024-04-13 06:54:23", "rate1": -3, "rate7": -4}, {"fans": 7129, "time": "2024-04-13 18:54:47", "rate1": -4, "rate7": -6}, {"fans": 7129, "time": "2024-04-14 06:54:24", "rate1": -3, "rate7": -8}, {"fans": 7130, "time": "2024-04-14 18:54:42", "rate1": 1, "rate7": -5}, {"fans": 7129, "time": "2024-04-15 06:54:19", "rate1": 0, "rate7": -9}, {"fans": 7130, "time": "2024-04-15 18:54:44", "rate1": 0, "rate7": -6}, {"fans": 7131, "time": "2024-04-16 06:54:30", "rate1": 2, "rate7": -7}, {"fans": 7131, "time": "2024-04-16 18:54:56", "rate1": 1, "rate7": -8}, {"fans": 7130, "time": "2024-04-17 06:54:39", "rate1": -1, "rate7": -6}, {"fans": 7130, "time": "2024-04-17 18:54:27", "rate1": -1, "rate7": -7}, {"fans": 7127, "time": "2024-04-18 06:55:01", "rate1": -3, "rate7": -7}, {"fans": 7127, "time": "2024-04-18 18:54:58", "rate1": -3, "rate7": -6}, {"fans": 7124, "time": "2024-04-19 06:55:22", "rate1": -3, "rate7": -11}, {"fans": 7124, "time": "2024-04-19 18:55:11", "rate1": -3, "rate7": -9}, {"fans": 7122, "time": "2024-04-20 06:55:06", "rate1": -2, "rate7": -10}, {"fans": 7118, "time": "2024-04-20 18:55:10", "rate1": -6, "rate7": -11}, {"fans": 7113, "time": "2024-04-21 06:55:09", "rate1": -9, "rate7": -16}, {"fans": 7117, "time": "2024-04-21 18:55:14", "rate1": -1, "rate7": -13}, {"fans": 7113, "time": "2024-04-22 06:55:46", "rate1": 0, "rate7": -16}, {"fans": 7109, "time": "2024-04-22 18:55:44", "rate1": -8, "rate7": -21}, {"fans": 7112, "time": "2024-04-23 06:55:09", "rate1": -1, "rate7": -19}, {"fans": 7107, "time": "2024-04-23 18:55:13", "rate1": -2, "rate7": -24}, {"fans": 7105, "time": "2024-04-24 06:55:20", "rate1": -7, "rate7": -25}, {"fans": 7104, "time": "2024-04-24 18:54:56", "rate1": -3, "rate7": -26}, {"fans": 7101, "time": "2024-04-25 06:55:06", "rate1": -4, "rate7": -26}, {"fans": 7099, "time": "2024-04-25 18:55:17", "rate1": -5, "rate7": -28}, {"fans": 7097, "time": "2024-04-26 06:54:53", "rate1": -4, "rate7": -27}, {"fans": 7095, "time": "2024-04-26 18:55:10", "rate1": -4, "rate7": -29}, {"fans": 7097, "time": "2024-04-27 06:55:25", "rate1": 0, "rate7": -25}, {"fans": 7095, "time": "2024-04-27 18:55:02", "rate1": 0, "rate7": -23}, {"fans": 7098, "time": "2024-04-28 06:55:16", "rate1": 1, "rate7": -15}, {"fans": 7098, "time": "2024-04-28 18:54:54", "rate1": 3, "rate7": -19}, {"fans": 7099, "time": "2024-04-29 06:55:08", "rate1": 1, "rate7": -14}, {"fans": 7101, "time": "2024-04-29 18:55:27", "rate1": 3, "rate7": -8}, {"fans": 7100, "time": "2024-04-30 06:54:59", "rate1": 1, "rate7": -12}, {"fans": 7095, "time": "2024-04-30 18:55:15", "rate1": -6, "rate7": -12}, {"fans": 7095, "time": "2024-05-01 06:55:29", "rate1": -5, "rate7": -10}, {"fans": 7095, "time": "2024-05-01 18:55:09", "rate1": 0, "rate7": -9}, {"fans": 7094, "time": "2024-05-02 06:55:20", "rate1": -1, "rate7": -7}, {"fans": 7093, "time": "2024-05-02 18:55:02", "rate1": -2, "rate7": -6}, {"fans": 7093, "time": "2024-05-03 06:55:15", "rate1": -1, "rate7": -4}, {"fans": 7093, "time": "2024-05-03 18:55:45", "rate1": 0, "rate7": -2}, {"fans": 7090, "time": "2024-05-04 06:55:18", "rate1": -3, "rate7": -7}, {"fans": 7091, "time": "2024-05-04 18:55:02", "rate1": -2, "rate7": -4}, {"fans": 7091, "time": "2024-05-05 06:55:15", "rate1": 1, "rate7": -7}, {"fans": 7089, "time": "2024-05-05 18:55:34", "rate1": -2, "rate7": -9}, {"fans": 7087, "time": "2024-05-06 06:55:08", "rate1": -4, "rate7": -12}, {"fans": 7085, "time": "2024-05-06 18:55:26", "rate1": -4, "rate7": -16}, {"fans": 7086, "time": "2024-05-07 06:55:00", "rate1": -1, "rate7": -14}, {"fans": 7084, "time": "2024-05-07 18:55:16", "rate1": -1, "rate7": -11}, {"fans": 7082, "time": "2024-05-08 06:54:50", "rate1": -4, "rate7": -13}, {"fans": 7081, "time": "2024-05-08 18:55:07", "rate1": -3, "rate7": -14}, {"fans": 7081, "time": "2024-05-09 06:55:18", "rate1": -1, "rate7": -13}, {"fans": 7081, "time": "2024-05-09 18:54:55", "rate1": 0, "rate7": -12}, {"fans": 7080, "time": "2024-05-10 06:55:08", "rate1": -1, "rate7": -13}, {"fans": 7080, "time": "2024-05-10 18:55:26", "rate1": -1, "rate7": -13}, {"fans": 7078, "time": "2024-05-11 06:54:59", "rate1": -2, "rate7": -12}, {"fans": 7078, "time": "2024-05-11 18:55:21", "rate1": -2, "rate7": -13}, {"fans": 7077, "time": "2024-05-12 06:54:56", "rate1": -1, "rate7": -14}, {"fans": 7078, "time": "2024-05-12 18:55:16", "rate1": 0, "rate7": -11}, {"fans": 7078, "time": "2024-05-13 06:54:50", "rate1": 1, "rate7": -9}, {"fans": 7078, "time": "2024-05-13 18:55:05", "rate1": 0, "rate7": -7}, {"fans": 7077, "time": "2024-05-14 06:55:32", "rate1": -1, "rate7": -9}, {"fans": 7074, "time": "2024-05-14 18:55:18", "rate1": -4, "rate7": -10}, {"fans": 7074, "time": "2024-05-15 06:55:02", "rate1": -3, "rate7": -8}, {"fans": 7070, "time": "2024-05-15 18:55:31", "rate1": -4, "rate7": -11}, {"fans": 7069, "time": "2024-05-16 06:55:20", "rate1": -5, "rate7": -12}, {"fans": 7069, "time": "2024-05-16 18:55:09", "rate1": -1, "rate7": -12}, {"fans": 7064, "time": "2024-05-17 06:55:02", "rate1": -5, "rate7": -16}, {"fans": 7060, "time": "2024-05-17 18:55:35", "rate1": -9, "rate7": -20}, {"fans": 7059, "time": "2024-05-18 06:55:26", "rate1": -5, "rate7": -19}, {"fans": 7056, "time": "2024-05-19 18:55:44", "rate1": -4, "rate7": -22}, {"fans": 7056, "time": "2024-05-20 06:55:40", "rate1": -3, "rate7": -21}, {"fans": 7057, "time": "2024-05-20 18:55:40", "rate1": 1, "rate7": -21}, {"fans": 7056, "time": "2024-05-21 06:55:37", "rate1": 0, "rate7": -22}, {"fans": 7056, "time": "2024-05-21 18:55:36", "rate1": -1, "rate7": -22}, {"fans": 7056, "time": "2024-05-22 06:55:33", "rate1": 0, "rate7": -21}, {"fans": 7057, "time": "2024-05-22 18:55:37", "rate1": 1, "rate7": -17}, {"fans": 7057, "time": "2024-05-23 06:55:40", "rate1": 1, "rate7": -17}, {"fans": 7058, "time": "2024-05-23 18:55:44", "rate1": 1, "rate7": -12}, {"fans": 7057, "time": "2024-05-24 06:55:47", "rate1": 0, "rate7": -12}, {"fans": 7058, "time": "2024-05-24 18:55:10", "rate1": 0, "rate7": -11}, {"fans": 7059, "time": "2024-05-25 06:55:08", "rate1": 2, "rate7": -5}, {"fans": 7056, "time": "2024-05-25 18:55:19", "rate1": -2, "rate7": -4}, {"fans": 7055, "time": "2024-05-26 06:55:24", "rate1": -4, "rate7": -4}, {"fans": 7053, "time": "2024-05-26 18:55:35", "rate1": -3, "rate7": -3}, {"fans": 7052, "time": "2024-05-27 06:55:48", "rate1": -3, "rate7": -4}, {"fans": 7053, "time": "2024-05-27 18:55:19", "rate1": 0, "rate7": -4}, {"fans": 7083, "time": "2024-05-28 06:55:25", "rate1": 31, "rate7": 27}, {"fans": 7090, "time": "2024-05-28 18:55:37", "rate1": 37, "rate7": 34}, {"fans": 7088, "time": "2024-05-29 06:55:52", "rate1": 5, "rate7": 32}, {"fans": 7089, "time": "2024-05-30 18:55:46", "rate1": -1, "rate7": 32}, {"fans": 7088, "time": "2024-05-31 06:56:02", "rate1": 0, "rate7": 31}, {"fans": 7078, "time": "2024-05-31 18:55:38", "rate1": -11, "rate7": 20}, {"fans": 7078, "time": "2024-06-01 06:55:50", "rate1": -10, "rate7": 21}, {"fans": 7082, "time": "2024-06-01 18:55:29", "rate1": 4, "rate7": 24}, {"fans": 7084, "time": "2024-06-02 06:55:45", "rate1": 6, "rate7": 25}, {"fans": 7088, "time": "2024-06-02 18:55:27", "rate1": 6, "rate7": 32}, {"fans": 7085, "time": "2024-06-03 06:55:47", "rate1": 1, "rate7": 30}, {"fans": 7092, "time": "2024-06-03 18:55:27", "rate1": 4, "rate7": 39}, {"fans": 7092, "time": "2024-06-04 06:55:50", "rate1": 7, "rate7": 40}, {"fans": 7092, "time": "2024-06-04 18:55:37", "rate1": 0, "rate7": 39}, {"fans": 7091, "time": "2024-06-05 06:56:02", "rate1": -1, "rate7": 8}, {"fans": 7093, "time": "2024-06-05 18:55:46", "rate1": 1, "rate7": 3}, {"fans": 7092, "time": "2024-06-06 06:55:29", "rate1": 1, "rate7": 4}, {"fans": 7089, "time": "2024-06-06 18:56:00", "rate1": -4, "rate7": 0}, {"fans": 7091, "time": "2024-06-07 06:55:47", "rate1": -1, "rate7": 3}, {"fans": 7091, "time": "2024-06-07 18:55:37", "rate1": 2, "rate7": 13}, {"fans": 7090, "time": "2024-06-08 06:56:13", "rate1": -1, "rate7": 12}, {"fans": 7090, "time": "2024-06-08 18:56:14", "rate1": -1, "rate7": 8}, {"fans": 7088, "time": "2024-06-09 06:56:18", "rate1": -2, "rate7": 4}, {"fans": 7088, "time": "2024-06-09 18:56:30", "rate1": -2, "rate7": 0}, {"fans": 7088, "time": "2024-06-10 06:55:57", "rate1": 0, "rate7": 3}, {"fans": 7086, "time": "2024-06-10 18:56:12", "rate1": -2, "rate7": -6}, {"fans": 7087, "time": "2024-06-11 06:56:27", "rate1": -1, "rate7": -5}, {"fans": 7088, "time": "2024-06-11 18:56:14", "rate1": 2, "rate7": -4}, {"fans": 7086, "time": "2024-06-12 06:56:37", "rate1": -1, "rate7": -5}, {"fans": 7088, "time": "2024-06-12 18:56:14", "rate1": 0, "rate7": -5}, {"fans": 7086, "time": "2024-06-13 06:56:07", "rate1": 0, "rate7": -6}, {"fans": 7086, "time": "2024-06-13 18:56:46", "rate1": -2, "rate7": -3}, {"fans": 7085, "time": "2024-06-14 06:56:39", "rate1": -1, "rate7": -6}, {"fans": 7083, "time": "2024-06-14 18:56:48", "rate1": -3, "rate7": -8}, {"fans": 7084, "time": "2024-06-15 06:56:11", "rate1": -1, "rate7": -6}, {"fans": 7084, "time": "2024-06-15 18:56:23", "rate1": 1, "rate7": -6}, {"fans": 7083, "time": "2024-06-16 06:56:33", "rate1": -1, "rate7": -5}, {"fans": 7079, "time": "2024-06-16 18:56:51", "rate1": -5, "rate7": -9}, {"fans": 7082, "time": "2024-06-17 06:56:28", "rate1": -1, "rate7": -6}, {"fans": 7085, "time": "2024-06-17 18:56:48", "rate1": 6, "rate7": -1}, {"fans": 7088, "time": "2024-06-18 06:56:32", "rate1": 6, "rate7": 1}, {"fans": 7090, "time": "2024-06-18 18:56:56", "rate1": 5, "rate7": 2}, {"fans": 7091, "time": "2024-06-19 06:56:38", "rate1": 3, "rate7": 5}, {"fans": 7095, "time": "2024-06-19 18:57:01", "rate1": 5, "rate7": 7}, {"fans": 7096, "time": "2024-06-20 06:56:41", "rate1": 5, "rate7": 10}, {"fans": 7098, "time": "2024-06-20 18:57:05", "rate1": 3, "rate7": 12}, {"fans": 7097, "time": "2024-06-21 06:56:45", "rate1": 1, "rate7": 12}, {"fans": 7096, "time": "2024-06-21 18:57:14", "rate1": -2, "rate7": 13}, {"fans": 7100, "time": "2024-06-22 06:57:14", "rate1": 3, "rate7": 16}, {"fans": 7099, "time": "2024-06-22 18:57:14", "rate1": 3, "rate7": 15}, {"fans": 7101, "time": "2024-06-23 06:57:14", "rate1": 1, "rate7": 18}, {"fans": 7102, "time": "2024-06-23 18:57:24", "rate1": 3, "rate7": 23}, {"fans": 7100, "time": "2024-06-24 06:56:50", "rate1": -1, "rate7": 18}, {"fans": 7101, "time": "2024-06-24 18:57:03", "rate1": -1, "rate7": 16}, {"fans": 7101, "time": "2024-06-25 06:57:21", "rate1": 1, "rate7": 13}, {"fans": 7088, "time": "2024-06-25 18:57:06", "rate1": -13, "rate7": -2}, {"fans": 7088, "time": "2024-06-26 06:57:46", "rate1": -13, "rate7": -3}, {"fans": 7083, "time": "2024-06-26 18:57:58", "rate1": -5, "rate7": -12}, {"fans": 7084, "time": "2024-06-27 06:57:24", "rate1": -4, "rate7": -12}, {"fans": 7086, "time": "2024-06-27 18:57:37", "rate1": 3, "rate7": -12}, {"fans": 7084, "time": "2024-06-28 06:57:55", "rate1": 0, "rate7": -13}, {"fans": 7085, "time": "2024-06-28 18:57:39", "rate1": -1, "rate7": -11}, {"fans": 7087, "time": "2024-06-29 06:57:20", "rate1": 3, "rate7": -13}, {"fans": 7087, "time": "2024-06-29 18:57:45", "rate1": 2, "rate7": -12}, {"fans": 7090, "time": "2024-06-30 06:57:31", "rate1": 3, "rate7": -11}, {"fans": 7089, "time": "2024-06-30 18:57:56", "rate1": 2, "rate7": -13}, {"fans": 7089, "time": "2024-07-01 06:57:46", "rate1": -1, "rate7": -11}, {"fans": 7086, "time": "2024-07-01 18:57:44", "rate1": -3, "rate7": -15}, {"fans": 7085, "time": "2024-07-02 06:57:35", "rate1": -4, "rate7": -16}, {"fans": 7085, "time": "2024-07-02 18:58:08", "rate1": -1, "rate7": -3}, {"fans": 7085, "time": "2024-07-03 06:57:59", "rate1": 0, "rate7": -3}, {"fans": 7088, "time": "2024-07-03 18:57:52", "rate1": 3, "rate7": 5}, {"fans": 7088, "time": "2024-07-04 06:57:56", "rate1": 3, "rate7": 4}, {"fans": 7089, "time": "2024-07-04 18:58:02", "rate1": 1, "rate7": 3}, {"fans": 7091, "time": "2024-07-05 06:58:16", "rate1": 3, "rate7": 7}, {"fans": 7090, "time": "2024-07-05 18:58:22", "rate1": 1, "rate7": 5}, {"fans": 7090, "time": "2024-07-06 06:57:49", "rate1": -1, "rate7": 3}, {"fans": 7092, "time": "2024-07-06 18:58:07", "rate1": 2, "rate7": 5}, {"fans": 7093, "time": "2024-07-07 06:58:14", "rate1": 3, "rate7": 3}, {"fans": 7094, "time": "2024-07-07 18:58:30", "rate1": 2, "rate7": 5}, {"fans": 7095, "time": "2024-07-08 06:58:09", "rate1": 2, "rate7": 6}, {"fans": 7095, "time": "2024-07-08 18:58:33", "rate1": 1, "rate7": 9}, {"fans": 7095, "time": "2024-07-09 06:58:33", "rate1": 0, "rate7": 10}, {"fans": 7097, "time": "2024-07-09 18:58:43", "rate1": 2, "rate7": 12}, {"fans": 7101, "time": "2024-07-10 06:58:50", "rate1": 6, "rate7": 16}, {"fans": 7102, "time": "2024-07-10 18:59:10", "rate1": 5, "rate7": 14}, {"fans": 7101, "time": "2024-07-11 06:58:51", "rate1": 0, "rate7": 13}, {"fans": 7099, "time": "2024-07-11 18:58:36", "rate1": -3, "rate7": 10}, {"fans": 7099, "time": "2024-07-12 06:58:59", "rate1": -2, "rate7": 8}, {"fans": 7099, "time": "2024-07-12 18:58:49", "rate1": 0, "rate7": 9}, {"fans": 7101, "time": "2024-07-13 06:59:16", "rate1": 2, "rate7": 11}, {"fans": 7101, "time": "2024-07-13 18:59:03", "rate1": 2, "rate7": 9}, {"fans": 7100, "time": "2024-07-14 06:58:50", "rate1": -1, "rate7": 7}, {"fans": 7101, "time": "2024-07-14 18:58:47", "rate1": 0, "rate7": 7}, {"fans": 7099, "time": "2024-07-15 06:58:47", "rate1": -1, "rate7": 4}, {"fans": 7096, "time": "2024-07-15 18:58:51", "rate1": -5, "rate7": 1}, {"fans": 7098, "time": "2024-07-16 06:58:59", "rate1": -1, "rate7": 3}, {"fans": 7100, "time": "2024-07-16 18:59:10", "rate1": 4, "rate7": 3}, {"fans": 7100, "time": "2024-07-17 06:59:26", "rate1": 2, "rate7": -1}, {"fans": 7102, "time": "2024-07-17 18:59:05", "rate1": 2, "rate7": 0}, {"fans": 7101, "time": "2024-07-18 06:59:30", "rate1": 1, "rate7": 0}, {"fans": 7103, "time": "2024-07-18 18:59:15", "rate1": 1, "rate7": 4}, {"fans": 7103, "time": "2024-07-19 06:59:39", "rate1": 2, "rate7": 4}, {"fans": 7103, "time": "2024-07-19 18:59:21", "rate1": 0, "rate7": 4}, {"fans": 7102, "time": "2024-07-20 06:59:05", "rate1": -1, "rate7": 1}, {"fans": 7101, "time": "2024-07-20 18:59:33", "rate1": -2, "rate7": 0}, {"fans": 7100, "time": "2024-07-21 06:59:23", "rate1": -2, "rate7": 0}, {"fans": 7102, "time": "2024-07-21 18:59:23", "rate1": 1, "rate7": 1}, {"fans": 7101, "time": "2024-07-22 06:59:15", "rate1": 1, "rate7": 2}, {"fans": 7101, "time": "2024-07-22 18:59:48", "rate1": -1, "rate7": 5}]